Workbook

Sheet Base Artigos
A1: ID | B1: Classificação | C1: Ano | D1: Autores | E1: Título | F1: Jounal | G1: SJR | H1: Citações | I1: País Aplicação | J1: País Autor Principal | K1: Abordagem Primpária | L1: Abordagem Secundária | M1: Plataforma de Resolução | N1: Objetivo Primário | O1: Objetivo Secundário | P1: Etapa da Cadeia Produtiva | Q1: Nível de Decisão | R1: DOI | S1: Link | T1: Palavras-chave autor
A2: 1 | B2: A | C2: 2019 | D2: Aguayo M.M.; Sarin S.C.; Cundiff J.S. | E2: A branch-and-price approach for a biomass feedstock logistics supply chain design problem | F2: IISE Transactions | G2: 0.862 | H2: 12 | I2: Estados Unidos | J2: Chile | K2: MILP | M2: CPLEX | N2: Min-C | O2: AGR, INST | P2: AGR, EST | Q2: TA | R2: 10.1080/24725854.2019.1589656 | S2: https://www.scopus.com/inward/record.uri?eid=2-s2.0-85066629282&doi=10.1080%2f24725854.2019.1589656&partnerID=40&md5=5698914ef7199ea4133fce1b173a01eb | T2: biomass logistics; branch-and-price; Cellulosic ethanol; facility location; lot-sizing
A3: 2 | B3: A | C3: 2023 | D3: Al Mohamed A.A.; Al Mohamed S.; Ahmad M. | E3: Solving aggregate production planning problem with uncertainty using fuzzy goal programming | F3: International Journal of Mathematics in Operational Research | G3: 0.272 | H3: 1 | I3: Síria | J3: Síria | K3: GP | L3: FL | M3: GAMS | N3: Min-C, Min-MO | O3: ARM, IND | P3: IND | Q3: TA | R3: 10.1504/IJMOR.2023.132838 | S3: https://www.scopus.com/inward/record.uri?eid=2-s2.0-85170406640&doi=10.1504%2fIJMOR.2023.132838&partnerID=40&md5=4912897a496be357a18091b25c770ea4 | T3: aggregate production planning; APP; FGP; fuzzy goal programming; fuzzy logic; goal programming; plastic industry
A4: 3 | B4: A | C4: 2021 | D4: Aliano Filho A.; Melo T.; Pato M.V. | E4: A bi-objective mathematical model for integrated planning of sugarcane harvesting and transport operations | F4: Computers and Operations Research | G4: 1.574 | H4: 13 | I4: Brasil | J4: Brasil | K4: MINLP | L4: MO | M4: JUMP/CPLEX | N4: Min-C, Min-T-AGR | O4: AGR | P4: AGR | Q4: TA | R4: 10.1016/j.cor.2021.105419 | S4: https://www.scopus.com/inward/record.uri?eid=2-s2.0-85107960409&doi=10.1016%2fj.cor.2021.105419&partnerID=40&md5=382589458131fe6684852de077af5cfd | T4: Integrated sugarcane harvesting and transport planning; Mixed-integer programming; Multi-objective optimization
A5: 4 | B5: A | C5: 2013 | D5: Awudu I.; Zhang J. | E5: Stochastic production planning for a biofuel supply chain under demand and price uncertainties | F5: Applied Energy | G5: 2.82 | H5: 122 | I5: Estados Unidos | J5: Estados Unidos | K5: SLP | M5: GAMS/MATLAB | N5: Max-LR | P5: AGR, IND, COM | Q5: TA | R5: 10.1016/j.apenergy.2012.09.025 | S5: https://www.scopus.com/inward/record.uri?eid=2-s2.0-84871810249&doi=10.1016%2fj.apenergy.2012.09.025&partnerID=40&md5=3a247c6286068a38cbf82e1f58a32fb1 | T5: Benders decomposition; Biofuel supply chain; Monte Carlo simulation; Stochastic programming
A6: 5 | B6: A | C6: 2009 | D6: Corsano G.; Aguirre P.A.; Montagna J.M. | E6: Multiperiod design and planning of multiproduct batch plants with mixed-product campaigns | F6: AIChE Journal | G6: 0.734 | H6: 5 | I6: Não Especificado | J6: Argentina | K6: MINLP | M6: GAMS | N6: Max-LR | P6: AGR, IND, EST | Q6: OP | R6: 10.1002/aic.11854 | S6: https://www.scopus.com/inward/record.uri?eid=2-s2.0-69049087107&doi=10.1002%2faic.11854&partnerID=40&md5=6c168665ffab8ee6df64f27a1f74debf | T6: Batch plant design; MINLP; Mixed-product campaigns; Multiperiod model; Production planning
A7: 6 | B7: A | C7: 2014 | D7: Corsano G.; Fumero Y.; Montagna J.M. | E7: Integrated decision making for the optimal bioethanol supply chain | F7: Energy Conversion and Management | G7: 2.553 | H7: 10 | I7: Não Especificado | J7: Argentina | K7: MILP | M7: GAMS | N7: Max-LR | P7: AGR, IND, EST | Q7: OP | R7: 10.1016/j.enconman.2014.04.090 | S7: https://www.scopus.com/inward/record.uri?eid=2-s2.0-84910075619&doi=10.1016%2fj.enconman.2014.04.090&partnerID=40&md5=a1d95054598a77fc254a92826334e881 | T7: Bioethanol production; Plant design; Production planning; Supply chain
A8: 7 | B8: A | C8: 2014 | D8: da Silva A.F.; Marins F.A.S. | E8: A Fuzzy Goal Programming model for solving aggregate production-planning problems under uncertainty: A case study in a Brazilian sugar mill | F8: Energy Economics | G8: 3.555 | H8: 50 | I8: Brasil | J8: Brasil | K8: GP | L8: FL | M8: GAMS/CPLEX | N8: Min-C, Max-P | O8: AGR, ARM, IND, MP, COM | P8: AGR, IND, COM | Q8: TA | R8: 10.1016/j.eneco.2014.07.005 | S8: https://www.scopus.com/inward/record.uri?eid=2-s2.0-84907853897&doi=10.1016%2fj.eneco.2014.07.005&partnerID=40&md5=b6cb58527aec159e6fa6e141369652a7 | T8: Aggregate production planning; Fuzzy goal programming; Goal programming; Sugar and ethanol mills
A9: 8 | B9: A | C9: 2013 | D9: Silva A.F. da; Marins F.A.S.; Barra Montevechi J.A. | E9: Multi-choice mixed integer goal programming optimization for real problems in a sugar and ethanol milling company | F9: Applied Mathematical Modelling | G9: 1 | H9: 40 | I9: Brasil | J9: Brasil | K9: GP | L9: MCMI | M9: GAMS/CPLEX | N9: Min-C, Max-P | O9: AGR, ARM, IND, MP | P9: AGR, IND | Q9: TA | R9: 10.1016/j.apm.2012.12.022 | S9: https://www.scopus.com/inward/record.uri?eid=2-s2.0-84875377451&doi=10.1016%2fj.apm.2012.12.022&partnerID=40&md5=f02fcec187df51170ecc27315df73f1b | T9: Aggregate production planning; Goal programming; Multi- Choice mixed integer goal programming; Multi-choice aspiration levels; Sugar and ethanol mills
A10: 9 | B10: A | C10: 2017 | D10: de Ávila Ribeiro Junqueira R.; Morabito R. | E10: Optimization approaches for sugarcane harvest front programming and scheduling | F10: Gestao e Producao | G10: 0.2 | H10: 16 | I10: Brasil | J10: Brasil | K10: MILP | M10: GAMS/CPLEX | N10: Min-C, Max-P, Min-T-AGR | O10: AGR | P10: AGR | Q10: OP | R10: 10.1590/0104-530X1882-16 | S10: https://www.scopus.com/inward/record.uri?eid=2-s2.0-85025139132&doi=10.1590%2f0104-530X1882-16&partnerID=40&md5=db90ddf501543c3f83096068037a53e3 | T10: Lot sizing and scheduling; Mixed integer programming; Programming and scheduling of harvest fronts; Sugarcane harvesting planning
A11: 10 | B11: A | C11: 2018 | D11: de Ávila Ribeiro Junqueira R.; Morabito R. | E11: Programming and scheduling sugarcane harvesting fronts: Model and solution methods for large-scale problems | F11: Gestao e Producao | G11: 0.2 | H11: 4 | I11: Brasil | J11: Brasil | K11: MILP | M11: GAMS/CPLEX | N11: Min-C | O11: AGR | P11: AGR | Q11: OP | R11: 10.1590/0104-530X2647-16 | S11: https://www.scopus.com/inward/record.uri?eid=2-s2.0-85045447528&doi=10.1590%2f0104-530X2647-16&partnerID=40&md5=b5fd1133a34f9a34589e2d5ffaafcd40 | T11: Mixed integer programming; Production lot sizing and scheduling; Relax-and-fix and fix-and-optimize heuristics; Sugarcane harvest programming
A12: 11 | B12: A | C12: 2019 | D12: de Ávila Ribeiro Junqueira R.; Morabito R. | E12: Modeling and solving a sugarcane harvest front scheduling problem | F12: International Journal of Production Economics | G12: 3.074 | H12: 40 | I12: Brasil | J12: Brasil | K12: MILP | M12: GAMS/CPLEX | N12: Min-C | O12: AGR | P12: AGR | Q12: TA | R12: 10.1016/j.ijpe.2019.03.009 | S12: https://www.scopus.com/inward/record.uri?eid=2-s2.0-85063589946&doi=10.1016%2fj.ijpe.2019.03.009&partnerID=40&md5=a12806fadb0be0553f1b9d0e75d81354 | T12: Case study; Logistics scheduling; Optimization approach; Sugarcane harvest front; Sugarmills; Validation process
A13: 12 | B13: A | C13: 2009 | D13: de Paiva R.P.O.; Morabito R. | E13: An optimization model for the aggregate production planning of a Brazilian sugar and ethanol milling company | F13: Annals of Operations Research | G13: 1.019 | H13: 51 | I13: Brasil | J13: Brasil | K13: MILP | M13: GAMS/CPLEX | N13: Max-LR | P13: AGR, IND | Q13: OP | R13: 10.1007/s10479-008-0428-9 | S13: https://www.scopus.com/inward/record.uri?eid=2-s2.0-64149125605&doi=10.1007%2fs10479-008-0428-9&partnerID=40&md5=7548dd3f373362d52f20ba43531f8c91 | T13: Aggregate production planning; Mixed integer optimization; Process selection; Production lot-sizing; Sugar and ethanol mills
A14: 13 | B14: A | C14: 2011 | D14: de Paiva R.P.O.; Morabito R. | E14: Stochastic robust optimization model applied to the aggregate production planning in mill cooperative socities in the sugar-energy sector | F14: Gestao e Producao | G14: 0.2 | H14: 6 | I14: Brasil | J14: Brasil | K14: SLP | L14: RO | M14: GAMS/CPLEX | N14: Max-LR | P14: IND, COM | Q14: TA, ES | R14: 10.1590/S0104-530X2011000400004 | S14: https://www.scopus.com/inward/record.uri?eid=2-s2.0-84856675703&doi=10.1590%2fS0104-530X2011000400004&partnerID=40&md5=199c3b71d25f358c30aa00b77d1f6dbb | T14: Aggregate production planning; Hierarchical planning; Stochastic robust programming; Sugarcane mills; Uncertainty analysis
A15: 14 | B15: A | C15: 2013 | D15: de Paiva R.P.O.; Morabito R. | E15: Optimization of the hierarchical production planning of a cooperative society of sugarcane milling companies; [Otimização do planejamento hierárquico da produção em usinas cooperadas do setor sucroenergético] | F15: Production | G15: 0.352 | H15: 4 | I15: Brasil | J15: Brasil | K15: MILP | M15: GAMS/CPLEX | N15: Max-LR | P15: IND, COM | Q15: TA, ES | R15: 10.1590/S0103-65132012005000077 | S15: https://www.scopus.com/inward/record.uri?eid=2-s2.0-84886552472&doi=10.1590%2fS0103-65132012005000077&partnerID=40&md5=f5b753a9bd3304102bb0cd8145474047 | T15: Aggregate production planning; Hierarchical planning; Mixed integer linear optimization; Sugarcane mills
A16: 15 | B16: A | C16: 2014 | D16: de Paiva R.P.O.; Morabito R. | E16: Hierarchical production planning for sugarcane milling companies: Robust optimization model; [Planejamento hierárquico da produção em usinas de açúcar e álcool: Modelagem de otimização robusta] | F16: Production | G16: 0.352 | H16: 3 | I16: Brasil | J16: Brasil | K16: MILP | L16: RO | M16: GAMS/CPLEX | N16: Max-LR | P16: AGR, IND | Q16: TA | R16: 10.1590/S0103-65132013005000032 | S16: https://www.scopus.com/inward/record.uri?eid=2-s2.0-84905180400&doi=10.1590%2fS0103-65132013005000032&partnerID=40&md5=11fdc50c66ee89ce72213dd34c6ce6ec | T16: Aggregate production planning; Hierarchical production planning; Mixed integer linear programming; Robust optimization; Sugarcane mills; Uncertainty analysis
A17: 16 | B17: A | C17: 2023 | D17: de Paiva R.P.O.; Rocco C.D.; Morabito R. | E17: A hierarchical supply chain model for the sugar–alcohol energy sector with robust optimization analysis | F17: International Transactions in Operational Research | G17: 1.027 | H17: 4 | I17: Brasil | J17: Brasil | K17: MILP | L17: RO | M17: CPLEX | N17: Max-LR | P17: AGR, IND | Q17: TA, ES | R17: 10.1111/itor.12909 | S17: https://www.scopus.com/inward/record.uri?eid=2-s2.0-85096878415&doi=10.1111%2fitor.12909&partnerID=40&md5=f838f5685e6d8194fa58d6a2b2db6313 | T17: hierarchical production planning; mixed-integer programming; robust optimization; sucroenergetic agroindustry; sugarcane; supply chain planning
A18: 17 | B18: A | C18: 2024 | D18: Hafezi N.; Sheikhdavoodi M.J.; Bahrami H.; Alavi S.E. | E18: Optimization of Harvesting Priority of Sugarcane Farms by the Generalized Assignment Problem | F18: Sugar Tech | G18: 0.451 | H18: 0 | I18: Irã | J18: Irã | K18: MILP | L18: FL | M18: GAMS/CPLEX | N18: Max-P | O18: AGR | P18: AGR | Q18: TA | R18: 10.1007/s12355-023-01336-2 | S18: https://www.scopus.com/inward/record.uri?eid=2-s2.0-85180642228&doi=10.1007%2fs12355-023-01336-2&partnerID=40&md5=613bd353d7aa58e5ca53c386c2cee26f | T18: Harvesting time optimization; Mixed integer programming; Neuro-fuzzy inference system; Sugarcane
A19: 18 | B19: A | C19: 2015 | D19: Kantas A.B.; Cobuloglu H.I.; Büyüktahtakn I.E. | E19: Multi-source capacitated lot-sizing for economically viable and clean biofuel production | F19: Journal of Cleaner Production | G19: 2.058 | H19: 26 | I19: Estados Unidos | J19: Estados Unidos | K19: MILP | M19: ILOG/CPLEX | N19: Min-C, Min-IA | O19: ARM, MP, INST | P19: AGR, IND | Q19: TA | R19: 10.1016/j.jclepro.2015.02.001 | S19: https://www.scopus.com/inward/record.uri?eid=2-s2.0-84928768228&doi=10.1016%2fj.jclepro.2015.02.001&partnerID=40&md5=15fc26072e55b1570a5109d825726e84 | T19: Biofuel; CO2 emissions; Mixed-integer; optimization; Production planning; Sustainability; Water usage
A20: 19 | B20: A | C20: 2020 | D20: Li X.; Jin X.; Lu S.; Li Z.; Wang Y.; Cao J. | E20: Carbon-efficient production scheduling of a bioethanol plant considering diversified feedstock pelletization density: A case study | F20: Processes | G20: 0.525 | H20: 1 | I20: China | J20: China | K20: MILP | L20: MO | M20: LINGO | N20: Max-LR, Min-IA | P20: AGR, IND | Q20: OP | R20: 10.3390/PR8091189 | S20: https://www.scopus.com/inward/record.uri?eid=2-s2.0-85092094522&doi=10.3390%2fPR8091189&partnerID=40&md5=6ff1f4447942e7ccc373334ed5fdcc3a | T20: Bioethanol plant; Carbon emission; Dual-objective optimization; Scheduling
A21: 20 | B21: A | C21: 2022 | D21: Li X.; Lu S.; Li Z.; Wang Y.; Zhu L. | E21: Modeling and optimization of bioethanol production planning under hybrid uncertainty: A heuristic multi-stage stochastic programming approach | F21: Energy | G21: 2.11 | H21: 12 | I21: China | J21: China | K21: SLP | M21: LINGO/MATLAB | N21: Min-C | O21: ARM, IND, MP, COM | P21: AGR, IND, COM | Q21: OP | R21: 10.1016/j.energy.2022.123285 | S21: https://www.scopus.com/inward/record.uri?eid=2-s2.0-85123736368&doi=10.1016%2fj.energy.2022.123285&partnerID=40&md5=da6cbcda171e6fa9f327c8263bf3d580 | T21: Bioethanol plant; Heuristic decomposition; Hybrid uncertainty; Mixed multi-stage optimization; Production planning
A22: 21 | B22: A | C22: 2021 | D22: Poltroniere S.C.; Aliano Filho A.; Caversan A.S.; Balbo A.R.; Florentino H.D.O. | E22: Integrated planning for planting and harvesting sugarcane and energy-cane for the production of sucrose and energy | F22: Computers and Electronics in Agriculture | G22: 1.735 | H22: 14 | I22: Brasil | J22: Brasil | K22: MILP | M22: JUMP/CPLEX | N22: Max-P | O22: AGR | P22: AGR | Q22: TA | R22: 10.1016/j.compag.2020.105956 | S22: https://www.scopus.com/inward/record.uri?eid=2-s2.0-85102558107&doi=10.1016%2fj.compag.2020.105956&partnerID=40&md5=e341dc723c32bf132c339236564e6513 | T22: Energy-cane; Fix-and-optimize; Mathematical optimization; Relax-and-fix; Sugarcane
A23: 22 | B23: A | C23: 2019 | D23: Saadati M.; Hosseininezhad S.J. | E23: Designing a hub location model in a bagasse-based bioethanol supply chain network in Iran (case study: Iran sugar industry) | F23: Biomass and Bioenergy | G23: 1.107 | H23: 20 | I23: Irã | J23: Irã | K23: MILP | L23: MO | M23: GAMS/CPLEX | N23: Min-C, Min-IA | O23: AGR, ARM, IND, MP, INST | P23: EST | Q23: TA, ES | R23: 10.1016/j.biombioe.2019.01.013 | S23: https://www.scopus.com/inward/record.uri?eid=2-s2.0-85061054948&doi=10.1016%2fj.biombioe.2019.01.013&partnerID=40&md5=41d1fc458d170af3a2034fb3fc7fc0de | T23: Bagasse; Bagasse-based bio-ethanol; Hub location model; Second-generation bioethanol
A24: 23 | B24: A | C24: 2012 | D24: You F.; Tao L.; Graziano D.J.; Snyder S.W. | E24: Optimal design of sustainable cellulosic biofuel supply chains: Multiobjective optimization coupled with life cycle assessment and input-output analysis | F24: AIChE Journal | G24: 0.734 | H24: 602 | I24: Estados Unidos | J24: Estados Unidos | K24: MILP | L24: MO | M24: GAMS/CPLEX | N24: Min-C, Min-IA, Max-EMP | O24: AGR, ARM, IND, INST, COM | P24: AGR, IND, COM, EST | Q24: TA | R24: 10.1002/aic.12637 | S24: https://www.scopus.com/inward/record.uri?eid=2-s2.0-80052359753&doi=10.1002%2faic.12637&partnerID=40&md5=5750c8e9fda0ae83c38a59510192ad22 | T24: Biofuel supply chain; Input-output analysis; Life cycle analysis; Multiobjective optimization; Planning; Sustainability
B25: B *C | C25: 2017 | D25: Albernas-Carvajal Y.; Corsano G.; González Cortés M.; González Suárez E. | E25: Preliminary design for simultaneous saccharification and fermentation stages for ethanol production from sugar cane bagasse | F25: Chemical Engineering Research and Design | H25: 7 | R25: 10.1016/j.cherd.2017.08.029 | S25: https://www.scopus.com/inward/record.uri?eid=2-s2.0-85031717429&doi=10.1016%2fj.cherd.2017.08.029&partnerID=40&md5=b214c5ecc34cc49226d1c1ac8c3b086a | T25: Batch design; Lignocellulosic ethanol; Optimization; Simultaneous saccharification and fermentation
B26: B *C | C26: 2015 | D26: Bhargava A.K.; Singh S.R.; Bansal D. | E26: Production planning using fuzzy meta-goal programming model | F26: Indian Journal of Science and Technology | H26: 3 | R26: 10.17485/ijst/2015/v8i34/70706 | S26: https://www.scopus.com/inward/record.uri?eid=2-s2.0-85000788450&doi=10.17485%2fijst%2f2015%2fv8i34%2f70706&partnerID=40&md5=2f30ba6813f122828ee598fd5f54d614 | T26: Fuzzy goal programming; Fuzzy meta-goal programming method; Manufacturing plant; Meta goals; Production planning
B27: C | C27: 2020 | D27: Blanco A.M.; Susana Moreno M.; Taraborelli C.; D'Angelo F.; Iturmendi F.; Alberto Bandoni J. | E27: Model-based decision support tools at Jugos S.A. concentrated fruit juice plant | F27: INFORMS Journal on Applied Analytics | H27: 0 | R27: 10.1287/INTE.2020.1045 | S27: https://www.scopus.com/inward/record.uri?eid=2-s2.0-85093853011&doi=10.1287%2fINTE.2020.1045&partnerID=40&md5=86d41bb99a69ee5d66468e3374da9a95 | T27: Batch scheduling; Concentrated fruit juice; Decision making; Mixed-integer nonlinear programming; Production planning
B28: B *C | C28: 2019 | D28: Daraei M.; Avelin A.; Dotzauer E.; Thorin E. | E28: Evaluation of biofuel production integrated with existing CHP plants and the impacts on production planning of the system – A case study | F28: Applied Energy | H28: 8 | R28: 10.1016/j.apenergy.2019.113461 | S28: https://www.scopus.com/inward/record.uri?eid=2-s2.0-85067284871&doi=10.1016%2fj.apenergy.2019.113461&partnerID=40&md5=96cc4ade59bcab2e1b1269098411e77c | T28: Electric vehicles; Energy systems; Mixed Integer Linear Programming; Optimization; Straw-based bioethanol; Transportation sector
B29: C | C29: 2016 | D29: Goharimanesh M.; Lashkaripour A.; Akbari A.A. | E29: Optimization of biodiesel production using multi-objective genetic algorithm | F29: Journal of Applied Science and Engineering | H29: 4 | R29: 10.6180/jase.2016.19.2.02 | S29: https://www.scopus.com/inward/record.uri?eid=2-s2.0-84975760574&doi=10.6180%2fjase.2016.19.2.02&partnerID=40&md5=1425b1688ea9909484d3b9d7f8e8a2df | T29: Biodiesel; Fuel; Genetic algorithm; Methyl ester; Optimization; Triglycerides
B30: C | C30: 2013 | D30: Gonçalves L.A.; Filho R.M. | E30: Alcohol production process modelling based on indicators using transactional software, industrial automation and manufacturing execution systems-MES | F30: Chemical Engineering Transactions | H30: 2 | R30: 10.3303/CET1332222 | S30: https://www.scopus.com/inward/record.uri?eid=2-s2.0-84879229989&doi=10.3303%2fCET1332222&partnerID=40&md5=f03c097971ec344c671af2d300907faf | T30: 0
B31: B *C | C31: 2024 | D31: Machado R.L.; Abreu M.R. | E31: Multi-objective optimization of the first and second-generation ethanol supply chain in Brazil using the water-energy-food-land nexus approach | F31: Renewable and Sustainable Energy Reviews | H31: 0 | R31: 10.1016/j.rser.2024.114299 | S31: https://www.scopus.com/inward/record.uri?eid=2-s2.0-85184776077&doi=10.1016%2fj.rser.2024.114299&partnerID=40&md5=658d1df40adacfbbeb5e985afdb9147e | T31: Analytic hierarchy process; Biofuel supply chain; Ethanol; MILP; Sustainable development goal 7; Water-energy-food-land nexus
B32: C | C32: 2021 | D32: Plangsrisakul K.; Somboonwiwat T.; Khompatraporn C. | E32: Make-to-order production planning with seasonal supply in canned pineapple industry | F32: Proceedings - European Council for Modelling and Simulation, ECMS | H32: 0 | S32: https://www.scopus.com/inward/record.uri?eid=2-s2.0-85108187122&partnerID=40&md5=dcfb65c6e0e1a26d9a0e730c88f0cf33 | T32: Canned pineapple industry; Make-to-order inventory; Multi-products multi-periods production planning; Pineapple color ratios; Seasonal raw materials
B33: C | C33: 2020 | D33: Rogowska D. | E33: Vapour pressure of butanol as a component of gasoline; [Prężność par butanolu jako komponentu benzyn silnikowych] | F33: Nafta - Gaz | H33: 0 | R33: 10.18668/NG.2020.05.07 | S33: https://www.scopus.com/inward/record.uri?eid=2-s2.0-85118885278&doi=10.18668%2fNG.2020.05.07&partnerID=40&md5=ed5554e5861014ff590ab50bd9961aea | T33: Biobuthanol; E10 gasoline; Vapour pressure blending numbers
B34: C | C34: 2018 | D34: Salawu E.Y.; Ajayi O.O.; Inegbenebor A.; Afolalu S.A.; Samson O. | E34: Pareto analysis of product quality failures and cost effects in bottling machines-a lean thinking solution for alcohol industry | F34: International Journal of Mechanical Engineering and Technology | H34: 7 | S34: https://www.scopus.com/inward/record.uri?eid=2-s2.0-85060438668&partnerID=40&md5=40baab08168cb888852ba5905b7aa4e8 | T34: Bottling machines; Failures; Production; Reliability
B35: C | C35: 2010 | D35: Sharma P.K.; Romagnoli J. | E35: An integrated framework for enterprise management - A synergistic approach towards sustainable biorefineries | F35: 10AIChE - 2010 AIChE Spring Meeting and 6th Global Congress on Process Safety | H35: 0 | S35: https://www.scopus.com/inward/record.uri?eid=2-s2.0-77956004249&partnerID=40&md5=ebb5e6bb64ce9631d288b4fb18e71d7a | T35: 0
B36: B *C | C36: 2016 | D36: Sudtachat K. | E36: A two-stage stochastic programming model for districting and transportation lot-size of sugarcane | F36: Proceedings of the International Conference on Industrial Engineering and Operations Management | H36: 0 | S36: https://www.scopus.com/inward/record.uri?eid=2-s2.0-85018450227&partnerID=40&md5=7af5ccc8cca050211f5799503244a080 | T36: Districting problem; Lot sizing problem; Sugarcane; Two-stage stochastic programming model
B37: C | C37: 2006 | D37: Zimberg B.; Testuri C.E. | E37: Stochastic analysis of crude oil procurement and processing under uncertain demand for bunker fuel oil | F37: International Transactions in Operational Research | H37: 5 | R37: 10.1111/j.1475-3995.2006.00554.x | S37: https://www.scopus.com/inward/record.uri?eid=2-s2.0-63849134995&doi=10.1111%2fj.1475-3995.2006.00554.x&partnerID=40&md5=b658073b1c7d573894a924e1ab1dbefb | T37: Production planning; Stochastic programming

Sheet Exclusão de duplicados
A1: Título | B1: D - Duplicado
A2: A bi-objective mathematical model for integrated planning of sugarcane harvesting and transport operations | B2: D
A3: A Fuzzy Goal Programming model for solving aggregate production-planning problems under uncertainty: A case study in a Brazilian sugar mill | B3: D
A4: A hierarchical supply chain model for the sugar–alcohol energy sector with robust optimization analysis | B4: D
A5: Alcohol production process modelling based on indicators using transactional software, industrial automation and manufacturing execution systems-MES | B5: D
A6: An optimization model for the aggregate production planning of a Brazilian sugar and ethanol milling company | B6: D
A7: Carbon-efficient production scheduling of a bioethanol plant considering diversified feedstock pelletization density: A case study | B7: D
A8: Designing a hub location model in a bagasse-based bioethanol supply chain network in Iran (case study: Iran sugar industry) | B8: D
A9: Hybrid simulation framework for the production management of an ethanol biorefinery | B9: D
A10: Integrated decision making for the optimal bioethanol supply chain | B10: D
A11: Integrated planning for planting and harvesting sugarcane and energy-cane for the production of sucrose and energy | B11: D
A12: Multi-choice mixed integer goal programming optimization for real problems in a sugar and ethanol milling company | B12: D
... A19: Vapour pressure of butanol as a component of gasoline | B19: D
A20: An optimization model for the aggregate production planning in alcohol and sugar mills | B20: D | P20: 10.1590/s0104-530x2007000100004 | Q20: https://www.scopus.com/inward/record.uri?eid=2-s2.0-34547371168&doi=10.1590%2fs0104-530x2007000100004&partnerID=40&md5=27f18fb49bfbcfa7f8242dfa7066497e | R20: Aggregate production planning; Integer optimization; Lot-sizing; Process selection; Sugar and alcohol mills

Sheet Siglas
A1: Tipo | B1: Sigla | C1: Descrição
A2: Abordagem Primária | B2: MILP | C2: Mixed Integer Linear Programming
A3: Abordagem Primária | B3: MINLP | C3: Mixed Integer Non-Linear Programming
A4: Abordagem Primária | B4: GP | C4: Goal Programming
A5: Abordagem Primária | B5: SLP | C5: Stochastic Linear Programming
A6: Abordagem Secundária | B6: MO | C6: Multi-Objective
A7: Abordagem Secundária | B7: RO | C7: Robust Optimization
A8: Abordagem Secundária | B8: FL | C8: Fuzzy Logic
A9: Abordagem Secundária | B9: MCMI | C9: Multi-Choice Mixed Integer
A10: Plataforma Resolução | B10: GA | C10: GAMS
A11: Plataforma Resolução | B11: CP | C11: CPLEX
A12: Plataforma Resolução | B12: JU | C12: JUMP
... A35: Nível de decisão | B35: ES | C35: Estratégico

Sheet Publicações por ano
A1: Ano | B1: Publicações
A2: 2009 | B2: =COUNTIFS('Base Artigos'!$C$2:$C$24,'Publicações por ano'!A2) -> 2
A3: 2010 | B3: =COUNTIFS('Base Artigos'!$C$2:$C$24,'Publicações por ano'!A3) -> 0
A4: 2011 | B4: =COUNTIFS('Base Artigos'!$C$2:$C$24,'Publicações por ano'!A4) -> 1
A5: 2012 | B5: =COUNTIFS('Base Artigos'!$C$2:$C$24,'Publicações por ano'!A5) -> 1
A6: 2013 | B6: =COUNTIFS('Base Artigos'!$C$2:$C$24,'Publicações por ano'!A6) -> 3
A7: 2014 | B7: =COUNTIFS('Base Artigos'!$C$2:$C$24,'Publicações por ano'!A7) -> 3
A8: 2015 | B8: =COUNTIFS('Base Artigos'!$C$2:$C$24,'Publicações por ano'!A8) -> 1
A9: 2016 | B9: =COUNTIFS('Base Artigos'!$C$2:$C$24,'Publicações por ano'!A9) -> 0
A10: 2017 | B10: =COUNTIFS('Base Artigos'!$C$2:$C$24,'Publicações por ano'!A10) -> 1
A11: 2018 | B11: =COUNTIFS('Base Artigos'!$C$2:$C$24,'Publicações por ano'!A11) -> 1
A12: 2019 | B12: =COUNTIFS('Base Artigos'!$C$2:$C$24,'Publicações por ano'!A12) -> 3
A13: 2020 | B13: =COUNTIFS('Base Artigos'!$C$2:$C$24,'Publicações por ano'!A13) -> 1
... A17: 2024 | B17: =COUNTIFS('Base Artigos'!$C$2:$C$24,'Publicações por ano'!A17) -> 1

Sheet Publicações país pesquisadores
A1: País | B1: Coautores | C1: Autor principal
A2: Alemanha | B2: =COUNTIFS($A$18:$A$85,"Coautor",$C$18:$C$85,A2) -> 1 | C2: =COUNTIFS($A$18:$A$85,"Principal",$C$18:$C$85,A2) -> 0
A3: Portugal | B3: =COUNTIFS($A$18:$A$85,"Coautor",$C$18:$C$85,A3) -> 1 | C3: =COUNTIFS($A$18:$A$85,"Principal",$C$18:$C$85,A3) -> 0
A4: Jordânia | B4: =COUNTIFS($A$18:$A$85,"Coautor",$C$18:$C$85,A4) -> 1 | C4: =COUNTIFS($A$18:$A$85,"Principal",$C$18:$C$85,A4) -> 0
A5: Chile | B5: =COUNTIFS($A$18:$A$85,"Coautor",$C$18:$C$85,A5) -> 0 | C5: =COUNTIFS($A$18:$A$85,"Principal",$C$18:$C$85,A5) -> 1
A6: Síria | B6: =COUNTIFS($A$18:$A$85,"Coautor",$C$18:$C$85,A6) -> 1 | C6: =COUNTIFS($A$18:$A$85,"Principal",$C$18:$C$85,A6) -> 1
A7: Irã | B7: =COUNTIFS($A$18:$A$85,"Coautor",$C$18:$C$85,A7) -> 4 | C7: =COUNTIFS($A$18:$A$85,"Principal",$C$18:$C$85,A7) -> 2
A8: Argentina | B8: =COUNTIFS($A$18:$A$85,"Coautor",$C$18:$C$85,A8) -> 4 | C8: =COUNTIFS($A$18:$A$85,"Principal",$C$18:$C$85,A8) -> 2
A9: China | B9: =COUNTIFS($A$18:$A$85,"Coautor",$C$18:$C$85,A9) -> 9 | C9: =COUNTIFS($A$18:$A$85,"Principal",$C$18:$C$85,A9) -> 2
A10: Estados Unidos | B10: =COUNTIFS($A$18:$A$85,"Coautor",$C$18:$C$85,A10) -> 8 | C10: =COUNTIFS($A$18:$A$85,"Principal",$C$18:$C$85,A10) -> 3
A11: Brasil | B11: =COUNTIFS($A$18:$A$85,"Coautor",$C$18:$C$85,A11) -> 16 | C11: =COUNTIFS($A$18:$A$85,"Principal",$C$18:$C$85,A11) -> 12
A17: Tipo | B17: Autor | C17: País | D17: Artigo
A18: Principal | B18: Aliano Filho, Angelo | C18: Brasil | D18: A bi-objective mathematical model for integrated planning of sugarcane harvesting and transport operations
A19: Coautor | B19: Melo, Teresa | C19: Alemanha | D19: A bi-objective mathematical model for integrated planning of sugarcane harvesting and transport operations
A20: Coautor | B20: Pato, Margarida Vaz | C20: Portugal | D20: A bi-objective mathematical model for integrated planning of sugarcane harvesting and transport operations
A21: Principal | B21: Aguayo, Maichel M. | C21: Chile | D21: A branch-and-price approach for a biomass feedstock logistics supply chain design problem
A22: Coautor | B22: Sarin, Subhash C. | C22: Estados Unidos | D22: A branch-and-price approach for a biomass feedstock logistics supply chain design problem
A23: Coautor | B23: Cundiff, John S. | C23: Estados Unidos | D23: A branch-and-price approach for a biomass feedstock logistics supply chain design problem
A24: Principal | B24: da Silva, Aneirson Francisco | C24: Brasil | D24: A Fuzzy Goal Programming model for solving aggregate production-planning problems under uncertainty: A case study in a Brazilian sugar mill
A25: Coautor | B25: Marins, Fernando Augusto Silva | C25: Brasil | D25: A Fuzzy Goal Programming model for solving aggregate production-planning problems under uncertainty: A case study in a Brazilian sugar mill
A26: Principal | B26: de Paiva, Rafael Piatti Oiticica | C26: Brasil | D26: A hierarchical supply chain model for the sugar–alcohol energy sector with robust optimization analysis
A27: Coautor | B27: Rocco, Cleber D. | C27: Brasil | D27: A hierarchical supply chain model for the sugar–alcohol energy sector with robust optimization analysis
A28: Coautor | B28: Morabito, Reinaldo | C28: Brasil | D28: A hierarchical supply chain model for the sugar–alcohol energy sector with robust optimization analysis
... A85: Coautor | B85: Hosseininezhad, Seyed Javad | C85: Irã | D85: Designing a hub location model in a bagasse-based bioethanol supply chain network in Iran (case study: Iran sugar industry)

Sheet Publicações país aplicação
A1: País aplicação | B1: Publicações
A2: Não especificado | B2: =COUNTIFS('Base Artigos'!$I$2:$I$24,'Publicações país aplicação'!A2) -> 2
A3: Síria | B3: =COUNTIFS('Base Artigos'!$I$2:$I$24,'Publicações país aplicação'!A3) -> 1
A4: Irã | B4: =COUNTIFS('Base Artigos'!$I$2:$I$24,'Publicações país aplicação'!A4) -> 2
A5: China | B5: =COUNTIFS('Base Artigos'!$I$2:$I$24,'Publicações país aplicação'!A5) -> 2
A6: Estados Unidos | B6: =COUNTIFS('Base Artigos'!$I$2:$I$24,'Publicações país aplicação'!A6) -> 4
A7: Brasil | B7: =COUNTIFS('Base Artigos'!$I$2:$I$24,'Publicações país aplicação'!A7) -> 12

Sheet Análise
A1: Authors | B1: Title | C1: DOI | D1: Link | E1: Problema | F1: ART-Abordagem | G1: Abordagem de modelagem | H1: ART-Técnicas | I1: Técnicas de resolução | J1: ART-Etapa | K1: Etapa da Cadeia produtiva | L1: ART-Plataf | M1: Plataforma resolução | N1: ART-Objetivo | O1: ART-Incerteza | P1: Função Objetivo | Q1: ART-Decisão | R1: Nível de decisão | S1: Obs.
A2: Aliano Filho A.; Melo T.; Pato M.V. | B2: A bi-objective mathematical model for integrated planning of sugarcane harvesting and transport operations | C2: 10.1016/j.cor.2021.105419 | D2: https://www.scopus.com/inward/record.uri?eid=2-s2.0-85107960409&doi=10.1016%2fj.cor.2021.105419&partnerID=40&md5=382589458131fe6684852de077af5cfd | E2: - O objetivo é desenvolver um plano tático para a implantação de equipamentos de colheita e transporte que defina os períodos para a execução das operações de colheita nos campos de cana-de-açúcar e o tipo de máquinas de colheita e veículos de transporte rodoviário a serem operados | F2: MINLP-MO | G2: - bi-objective mixed-integer non-linear programming - mixed-integer non-linear programming (MINLP) | H2: - Descrever multiobjetivo conflitante | I2: - Progressive Bounded Constraint (PBC) - Linearização - Soluções ótimas de Pareto são identificadas pelo método Progressive Bounded Constraint que é estendido ao problema em questão - Técnicas de linearização ? - Soluções lexicográficas ? - Branch-and-Bound ? | K2: Planejamento integrado colheita e transporte para planejamento multiperíodo | M2: - CPLEX - JuMP modeling language and embedded in the Julia programming language | N2: - Minimizar custo total de colheita e transporte - Minimizar o tempo total de colheita | P2: Bi-objetivo - Minimizar o custo total de colheita e transporte - Minimizar o tempo total de colheita | R2: Tático (temporada de colheita abril-dezembro) | S2: Falar deste artigo, pois fez uma busca na literatura, não uma revisão sistemática, mas para entender o tema | U2: Utilizar na referência da revisão sistemática
A3: Aguayo M.M.; Sarin S.C.; Cundiff J.S. | B3: A branch-and-price approach for a biomass feedstock logistics supply chain design problem | C3: 10.1080/24725854.2019.1589656 | D3: https://www.scopus.com/inward/record.uri?eid=2-s2.0-85066629282&doi=10.1080%2f24725854.2019.1589656&partnerID=40&md5=5698914ef7199ea4133fce1b173a01eb | E3: - Problema de localização e instalações multiperíodo - Problema de dimensionamento de lote capacitado de item único com instalações paralelas (CLSP-PF) e um problema de fluxo de rede - Neste artigo, abordamos esse problema e, em particular, focamos no design de uma cadeia de suprimentos de logística de matéria-prima econômica encontrada durante a produção de etanol à base de switchgrass (capim-rabo-de-raposa). - Verifica número de instalações de armazenamento (centros de distribuição e produtores rurais) a serem incluídos na cadeia de armazenamento e dimensiona o transporte até a usina de bioenergia - Restrições de localização e dimensionamento de lote | F3: MILP | G3: - Mixed-integer program | I3: - branch-and-price - Geração do limite inferior com heurística? - Dual stabilization | K3: Transporte de capim-rabo-de-raposa até a usina de bioenergia | M3: CPLEX | N3: - Minimizar custo total | P3: - captura nosso objetivo de minimizar o custo total incorrido pela propriedade dos conjuntos de equipamentos de carga e tratores-reboques, instalação de SSLs, mobilização de equipamentos, embarque de biomassa de SSLs para a usina de bioenergia e instalação de conjuntos de equipamentos de carga | T3: Remover?
A4: da Silva A.F.; Marins F.A.S. | B4: A Fuzzy Goal Programming model for solving aggregate production-planning problems under uncertainty: A case study in a Brazilian sugar mill | C4: 10.1016/j.eneco.2014.07.005 | D4: https://www.scopus.com/inward/record.uri?eid=2-s2.0-84907853897&doi=10.1016%2fj.eneco.2014.07.005&partnerID=40&md5=b6cb58527aec159e6fa6e141369652a7 | E4: - Problema e planejamento de produção agregado - Previsão de cana a ser colhida por fornecedor e a quantidade de cana a ser moída - Determina a quantidade de produtos a ser produzida em cada processo industrial - Custo de transporte do produto final para o cliente - O Modelo FGP retrata o processo de produção abrangente de açúcar, etanol, melaço e derivados, e considera as incertezas envolvidas na produção de etanol e açúcar. As tomadas de decisão, relacionadas às fases agrícola e logística, foram consideradas em um horizonte de planejamento semanal para incluir toda a temporada de colheita e os períodos entre as colheitas. A pesquisa forneceu resultados interessantes sobre decisões nas etapas agrícolas de corte, carregamento e transporte para fornecedores de cana-de-açúcar e, especialmente, nas decisões de moagem, cuja escolha do processo de produção inclui armazenamento e distribuição logística. | F4: GP-FL | G4: - Fuzzy Goal Programming model (FGP) | I4: - Método exato, diretamente no SOLVER - Programação por metas ? - Incertezas ? | K4: - Planejamento agregado - Integração das fases agrícola, industrial e logística em um modelo único, para apoiar a tomada de decisões durante as safras e períodos entre safras. - Fornecimento de matéria prima, transporte e produção industrial | M4: - software GAMS - General Algebraic Modeling System, versão 24.2.1, enquanto o Solver CPLEX 12.6 foi utilizado para encontrar uma solução ótima para o modelo | N4: - Maximizar a produção total de açúcar cristal - Maximizar a produção total de açúcar VVHP - Maximizar a produção total de açúcar VHP - Maximizar a produção total de etanol - Minimizar os custos totais de armazenamento - Minimizar os custos totais de transporte de matéria-prima dos fornecedores - Minimizar os custos totais de matéria-prima dos fornecedores - Minimizar os custos totais de processamento de matéria-prima - Minimizar os custos totais de distribuição aos clientes | P4: Multiobjetivo - Minimizar os custos de cada fase agroindustrial --Fornecimento de matéria-prima -- Transporte de cana-de-açúcar -- Processo de produção - Minimizar o custo total do estoque - Minimizar o custo total de distribuição dos produtos aos clientes - Maximizar a produção: --Açúcar Cristal --Açúcar VHP --Açúcar VVHP --Produção de etanol | R4: Estratégico ? Uma safra (período t (colheita e entre colheitas ou 52 semanas);
A5: de Paiva R.P.O.; Rocco C.D.; Morabito R. | B5: A hierarchical supply chain model for the sugar–alcohol energy sector with robust optimization analysis | C5: 10.1111/itor.12909 | D5: https://www.scopus.com/inward/record.uri?eid=2-s2.0-85096878415&doi=10.1111%2fitor.12909&partnerID=40&md5=f838f5685e6d8194fa58d6a2b2db6313 | E5: - O primeiro nível hierárquico do modelo da cadeia de suprimentos corresponde ao planejamento agregado da colheita, considerando todas as usinas da sociedade cooperativa, com foco nas principais decisões mensais sobre o mix de produção, armazenamento e políticas de vendas da sociedade cooperativa. No segundo nível, as decisões são menos agregadas, considerando o planejamento semanal da colheita e as configurações industriais de cada usina no sistema cooperativo para atender à demanda potencial do produto (açúcar, etanol e melaço) definida no primeiro nível do modelo. - 10 moinhos, 12 produtos, 12 meses, 25 semanas e 24 processos industriais. | F5: MILP-RO | G5: - Programação linear inteira mista com otimização robusta - Modelo linear - Abordagem de otimização robusta com dois parâmetros de incerteza (1º preço nominal dos produtos fabricados e vendidos; 2º matriz de rendimentos industrial) | I5: - Solver | K5: - Transporte, colheita, produção industrial e venda | M5: CPLEX | N5: -Maximizar lucro de venda dos produtos - Maximizar receitas | P5: Multiobjetivo - Modelo 1: maximizar o lucro de venda de todos os produtos de todas as fábricas e a energia exportada ao longo do horizonte de planejamento considerando custos de produção e armazenagem - Maximizar a margem de contribuição da cooperativa (todas as usinas) - Maximizar a margem de contribuição de cada usina ** - O V Ppt é um parâmetro de marketing que está dentro da função objetivo do PASUC/L1 e corresponde aos preços do açúcar e dos álcoois (índice p por produto) sujeitos aos derivativos das flutuações do mercado ao longo do tempo (índice t para mês), cuja análise de incerteza é criticamente importante para a lucratividade do negócio - O parâmetro Apkw é o matriz de rendimentos industriais em PASUC/L2. Representa o rendimento do produto p fabricado a partir do processo k na usina na semana w. A indexação por períodos (índice w para semana) traz para o modelo as características agrícolas e industriais, que variam ao longo da temporada de colheita, como o açúcar total recuperável (ATR) (parâmetro T RSuw) na usina u, o teor de fibra da cana-de-açúcar do fornecedor m (Fibermw) e o tempo útil de operação da moagem (ÿw) ao longo das semanas do horizonte de planejamento. - A função objetivo (1) do PASUC/L1 maximiza o lucro para o máximo esperado demanda (Dpt) da venda de todos os produtos produzidos em todas as fábricas ao longo dos períodos no horizonte de planejamento, considerando também os custos de produção e aqueles derivados da política de armazenagem - A função objetivo (22) maximiza a receita da venda de todos os produtos e energia exportados para a rede de um moinho associado à cooperativa do moinho, deduzindo os custos de produção e logística | R5: Estratégico e Tático | S5: - Utilizou conjunto de dados reais, diferente de Paiva Morabito 2014 que teve objetivo de validar os modelos - Descreve operação básica da indústria com uma figura simples - Diagrama de processo com base no Paiva e Morabito 2013
A6: de Paiva R.P.O.; Morabito R. | B6: An optimization model for the aggregate production planning in alcohol and sugar mills; [Um modelo de otimização para o planejamento agregado da produção em usinas de açúcar e álcool] | C6: 10.1590/s0104-530x2007000100004 | D6: https://www.scopus.com/inward/record.uri?eid=2-s2.0-34547371168&doi=10.1590%2fs0104-530x2007000100004&partnerID=40&md5=27f18fb49bfbcfa7f8242dfa7066497e | E6: - Este modelo se baseia nos modelos clássicos de seleção de processos e dimensionamento de lotes para representar o sistema de produção de açúcar, álcool e melaço, incluindo decisões da etapa agrícola, das fases de corte, carregamento e transporte de cana e, principalmente, decisões de moagem, escolha do processo produtivo e estoque dos produtos finais. As decisões são tomadas em períodos semanais e o horizonte de planejamento são as semanas de safra. | G6: - Modelo combinado de seleção de processo e dimensionamento de lotes | I6: -Solver | K6: - Quanto comprar de cana, corte, carregamento, transporte, produção industrial e estoque | M6: Linguagem de modelagem GAMS no CPLEX | P6: - maximizar a margem de contribuição agroindustrial de produção dos produtos p, por meio dos processos k, da matéria-prima m, do tipo de transporte da matéria-prima f e do local de estoque e, em todos os períodos t - Maximizar a margem de contribuição - O problema consiste em determinar o quanto produzir de cada produto em cada processo, de maneira a minimizar os custos de produção, sujeito às restrições de limitação de recursos e atendimento da demanda | R6: Estratégico ? - uma safra | S6: macro-operações envolvidas no processo de produção de uma usina (pesagem, estocagem, lavagem, preparo/moagem, clarificação do caldo, evaporação, cozimento/turbinação) e de uma destilaria (fermentação/centrifugação, destilação). Também podemos perceber as macro-perdas envolvidas na produção de açúcar e álcool (perdas na água de lavagem, no bagaço, na torta, na fermentação, na vinhaça e perdas indeterminadas) | T6: Utilizar como base para o modelo | U6: São iguais | V6: Remover duplicado
A7: de Paiva R.P.O.; Morabito R. | B7: An optimization model for the aggregate production planning of a Brazilian sugar and ethanol milling company | C7: 10.1007/s10479-008-0428-9 | D7: https://www.scopus.com/inward/record.uri?eid=2-s2.0-64149125605&doi=10.1007%2fs10479-008-0428-9&partnerID=40&md5=7548dd3f373362d52f20ba43531f8c91 | E7: - o modelo proposto neste artigo visa utilizar uma perspectiva agregada de toda a cadeia de suprimentos agroindustrial para auxiliar os tomadores de decisão na seleção processos industriais utilizados na produção de açúcar, etanol e melaço, bem como na determinação das quantidades de cana-de-açúcar moída, na seleção de fornecedores de cana-de-açúcar e na determinação de fornecedores de transporte e as decisões de armazenagem relacionadas aos produtos finais. No estudo de caso que está sendo considerado, essas decisões são tomadas semanalmente e o horizonte de planejamento é toda a temporada de colheita da cana-de-açúcar (ou seja, 23 semanas). | F7: MILP | G7: -Programação inteira mista | I7: - Modelo combinado de seleção de processo e dimensionamento de lotes | K7: - Quanto comprar de cana, corte, carregamento, transporte, produção industrial e estoque | M7: Linguagem de modelagem GAMS no CPLEX | N7: -Maximizar receita variável total de todos os setores agroindustriais e etapas da usina | P7: - A função objetivo (1) maximiza a receita variável total de todos os setores agroindustriais. etapas da usina. Esta função objetivo auxilia o tomador de decisão a determinar a quantidade de cana-de-açúcar moída, a seleção de fornecedores de cana-de-açúcar, a seleção de cana-de-açúcar fornecedores de transporte, a seleção do processo industrial utilizado na produção de açúcar, etanol e melaço e as decisões de armazenagem relacionadas aos produtos finais visando atingir a receita máxima em toda a temporada de colheita | R7: Estratégico ? - uma safra | T7: Utilizar como base para o modelo | U7: São iguais | V7: 669 mil unidades monetárias
A8: Li X.; Jin X.; Lu S.; Li Z.; Wang Y.; Cao J. | B8: Carbon-efficient production scheduling of a bioethanol plant considering diversified feedstock pelletization density: A case study | C8: 10.3390/PR8091189 | D8: https://www.scopus.com/inward/record.uri?eid=2-s2.0-85092094522&doi=10.3390%2fPR8091189&partnerID=40&md5=6ff1f4447942e7ccc373334ed5fdcc3a | E8: - O caso considera tanto a palha de milho quanto a palha de trigo como matérias-primas de biomassa, e adota duas técnicas de enfardamento para transformar as matérias-primas em fardos retangulares e redondos, respectivamente. A palha de milho, a palha de trigo e outros resíduos deixados após a colheita podem ser usados ​​para a produção de bioetanol durante todo o ano. - Este artigo apresenta um modelo específico de otimização de programação de produção com eficiência em carbono para a planta de bioetanol e propõe uma abordagem de otimização de objetivo duplo para demonstrar a eficácia em decisões flexíveis entre emissão de carbono e lucro. Os efeitos de diferentes matérias-primas de biomassa com densidade de peletização opcional e métodos de pré-tratamento na programação da produção são analisados. | F8: MILP-MO | G8: - mixed integer linear programming (MILP) - bi-objetivo | I8: -Solver - método ponderado por associação - Pareto | K8: - Produção de bioetanol - Aquisição de matéria-prima, embalagem e transporte da matéria até a usina de bioetanol - A usina de bioetanol adquire as matérias-primas dos fornecedores de acordo com a demanda de produção. (Suprimentos..) - custo de compra, armazenamento da matéria, transporte, pré-tratamento, armazenamento do produto intermediário e fermentação do etanol | M8: - LINGO | N8: -Maximizar o lucro total - Minimizar as emissões de carbono | P8: - bi-objetivo - O problema de programação da produção de biocombustível de etanol acima mencionado avalia dois objetivos principais de otimização, eles são o lucro total e a emissão de carbono. Como esses dois aspectos são medidos por escalas diferentes, um modelo de otimização de objetivo duplo é introduzido, que usa o método de ponderação de associação para resolver e, então, é otimizado simultaneamente - Primeiramente, o planejamento da produção e programação do transporte, armazenamento, pré-tratamento e fabricação de etanol da usina de bioetanol são totalmente considerados. Em segundo lugar, as emissões de carbono no processo de fabricação de etanol são integradas ao modelo para formar um modelo de otimização de objetivo duplo que otimiza simultaneamente o plano de produção e as emissões de carbono | S8: - Para lidar com esse problema, este artigo primeiro estabelece um modelo MILP de programação do processo de produção de bioetanol, considerando o trade-off entre emissões de carbono e lucros. Em segundo lugar, com base na influência de diferentes esquemas de pré-tratamento no rendimento de bioetanol no processo de produção de bioetanol, a influência dos esquemas de pré-tratamento no lucro total com condições de demanda variáveis é estudada. Finalmente, uma abordagem de otimização de objetivo duplo com base na associação ponderada é aplicada para equilibrar quantitativamente os efeitos da emissão de carbono na programação da produção e, com base nisso, fornece uma ferramenta com eficiência de carbono para projetar a programação da produção da planta de bioetanol. | T8: planta de bioetanol, palha de milho e de trigo
A9: Saadati M.; Hosseininezhad S.J. | B9: Designing a hub location model in a bagasse-based bioethanol supply chain network in Iran (case study: Iran sugar industry) | C9: 10.1016/j.biombioe.2019.01.013 | D9: https://www.scopus.com/inward/record.uri?eid=2-s2.0-85061054948&doi=10.1016%2fj.biombioe.2019.01.013&partnerID=40&md5=41d1fc458d170af3a2034fb3fc7fc0de | E9: - o estudo atual propõe um modelo de programação linear inteira mista multiobjetivo para localizar instalações de hub na rede da cadeia de suprimentos de bioetanol à base de bagaço. A metodologia proposta é capaz de determinar o número ideal de locais, a capacidade das instalações, o modo de transporte apropriado, o fluxo de material entre cada par de nós e o planejamento da produção em diferentes períodos. Para ilustrar a aplicação do modelo desenvolvido, um estudo de caso do Irã é conduzido e o desempenho do modelo desenvolvido é avaliado usando dados do mundo real relacionados à indústria açucareira do Irã. - Este artigo desenvolve um modelo de hub-and-spoke para uma planta de beneficiamento de bagaço rede da cadeia de suprimentos de bioetanol. - A rede é composta por cinco escalões: centros de abastecimento, centros de pré-processamento, biorrefinarias, instalações de hub e centros de demanda. | F9: MILP-MO | G9: - mixed integer linear programming (MILP) - multi-objetivo | I9: - Soluções Pareto-ótimas são exploradas em vez de soluções ótimas e posteriormente, o tradeoff entre duas funções objetivo - O trade-off entre a minimização dos custos totais e emissão de CO2 e o diagrama de Pareto resultante do método e-constraint - é feita uma análise de sensibilidade em dois dos parâmetros do modelo (custo de importação, estabelecimento do hub) | J9: AGR-IND-COM | K9: - Neste artigo, é apresentado um modelo MILP, incluindo alocação de localização de instalações, planejamento de distribuição e planejamento de produção. - Determinar o número ideal de locais, capacidade das instalações, modo de transporte adequado, planejamento de produção e importação e fluxo de materiais entre componentes da cadeia de suprimentos em diferentes períodos de tempo. | M9: Linguagem de modelagem GAMS no CPLEX | N9: -Minimizar custos transporte, instalação, importação de matéria-prima, produção, estoque -Minimizar emissões de carbono | P9: - multi-objetivo - MILP proposto para minimizar custos e redução de CO2 simultâneamente - O objetivo do planejamento é minimizar o custo total e a emissão de CO2 e rede de cadeia de fornecimento de bioetanol à base de bagaço simultaneamente | R9: - Estratégica e tática - O modelo proposto aborda as seguintes decisões estratégicas e táticas da cadeia de suprimentos: (1) decisões estratégicas de nível estratégico que tratam da determinação do número, capacidade e localização de centros de pré-processamento, biorrefinarias e hubs. As decisões em níveis táticos são atribuídas à programação de produção, como quantidade de produção, nível de estoque e número de materiais transportados entre diferentes níveis da cadeia em diferentes períodos.
A10: de Paiva R.P.O.; Morabito R. | B10: Hierarchical production planning for sugarcane milling companies: Robust optimization model; [Planejamento hierárquico da produção em usinas de açúcar e álcool: Modelagem de otimização robusta] | C10: 10.1590/S0103-65132013005000032 | D10: https://www.scopus.com/inward/record.uri?eid=2-s2.0-84905180400&doi=10.1590%2fS0103-65132013005000032&partnerID=40&md5=11fdc50c66ee89ce72213dd34c6ce6ec | E10: - Recentemente Paiva (2009) e Paiva e Morabito (2012) apresentaram um modelo de otimização determinístico para o problema de planejamento agregado da produção em usinas cooperadas do setor sucroenergético. Esta modelagem, denominada PASUC (Planejamento Agregado de Safra em Usinas Cooperadas do Setor Sucroenergético), considera a relação hierárquica existente entre o planejamento anual da cooperativa e o planejamento tático de safra das usinas cooperadas, propiciando a análise integrada do planejamento de safra em um grupo de usinas. | F10: MILP-RO | G10: - Programação linear e programação linear inteira mista - modelo de otimização robusta com incerteza | K10: -No nível de decisão da cooperativa (PASUC/N1), um modelo de programação linear multiproduto, dois estágios, dinâmico, capacitado, com horizonte de planejamento anual e agregação temporal mensal determina a quantidade e o mix de produção (PUput) das usinas, a política de estoque (Ipet) e a política de atendimento da demanda (Dpt) - No nível de decisão de cada usina cooperada (PASUC/N2), um modelo de programação inteira mista multiproduto, monoestágio, multiprocesso, dinâmico, capacitado, com horizonte de planejamento do período de moagem (aproximadamente 6 meses) e agregação temporal semanal combina decisões de dimensionamento e sequenciamento dos lotes de produção para o atendimento das metas do primeiro nível hierárquico | M10: Linguagem de modelagem GAMS no CPLEX | N10: -Maximizar a margem de contribuição ao lucro da produção de todos os produtos em todas as usinas e em todos os períodos - Maximizar a margem de contribuição da produção por meio dos processos, da matéria-prima e do tipo de transporte da matéria-prima, em todos os períodos ** incluindo as incertezas do preço de venda e da eficiência industrial | P10: - Essas variáveis devem ser calculadas de forma que a margem de contribuição do grupo seja maximizada -O objetivo é obter um plano tático de safra que proporcione a máxima margem de contribuição, respeitando as restrições de previsão de safra, capacidade de transporte, capacidade de estoque, fluxo de caixa positivo e necessidade de energia térmica e elétrica nos processos industriais. | Q10: -Tático - Operacional | R10: - Tático e Operacional | S10: Cita trabalhos anteriores deles de 2011
A11: Kim S.; Kim S. | B11: Hybrid simulation framework for the production management of an ethanol biorefinery | C11: 10.1016/j.rser.2021.111911 | D11: https://www.scopus.com/inward/record.uri?eid=2-s2.0-85119432925&doi=10.1016%2fj.rser.2021.111911&partnerID=40&md5=1a15026c6c014b2223443a4f97c6f886 | E11: - neste estudo, propomos uma estrutura de simulação híbrida para o planejamento de produção sustentável de uma refinaria de biocombustível para sua produção de etanol à base de grãos. E este estudo será a primeira tentativa de avaliar o desempenho econômico de toda a cadeia de suprimentos, desde a plantação de matéria-prima para biocombustíveis até a produção de etanol. | I11: -Para incorporar as interações dinâmicas e contínuas dentro de uma instalação, adotamos simulação baseada em agentes (ABS - agent-based simulation) neste estudo. ABS é um paradigma de simulação contínua equipado com algoritmos de inteligência artificial (IA) para tomar decisões sobre múltiplos agentes - Existem oito operações principais em uma refinaria, e as operações estão intimamente conectadas entre si. Modelamos as interações entre as operações e as atividades de transporte entre fazendas de matéria-prima e uma refinaria por meio do ABS, usando o software AnyLogic® para a modelagem. - adotamos o OptQuest®, que é um mecanismo de otimização meta-heurística, para encontrar uma taxa de produção apropriada com o custo operacional mínimo - Para validação do modelo, comparamos os rendimentos simulados de milho com os rendimentos medidos de 2015 a 2018. Para avaliar a calibração e validação do modelo, calculamos o viés percentual (PBIAS), o erro quadrático médio (RMSE) e o coeficiente de correlação de determinação de Pearson (R2 ). | M11: - Para uma estimativa precisa da distância de viagem entre fazendas e uma refinaria, usamos o módulo GIS no AnyLogic® AnyLogic | S11: Não faz simulação, excluir
A12: Corsano G.; Fumero Y.; Montagna J.M. | B12: Integrated decision making for the optimal bioethanol supply chain | C12: 10.1016/j.enconman.2014.04.090 | D12: https://www.scopus.com/inward/record.uri?eid=2-s2.0-84910075619&doi=10.1016%2fj.enconman.2014.04.090&partnerID=40&md5=a1d95054598a77fc254a92826334e881 | E12: -O modelo proposto neste trabalho determina simultaneamente a estrutura de uma cadeia de suprimentos de três escalões (locais de matéria-prima, instalações de produção e zonas de clientes), o projeto de cada planta instalada e considerações operacionais por meio de campanhas de produção. A produção de levedura é considerada para reduzir o impacto ambiental negativo causado por resíduos de bioetanol. | F12: MILP | G12: - mixed integer linear programming (MILP) - Their approach establishes the optimal plant configuration (unit dimensions, units duplication) and the production planning using mixed product campaigns (MPC) (number of batches of each product in the campaign and its sequencing) | I12: -Solver | K12: -compreende três escalões: matéria-prima locais de materiais, instalações de produção de etanol/levedura e zonas de clientes. - Cada planta instalada pode produzir os três produtos: levedura torula, etanol e levedura de padeiro, e eles têm as etapas de processo | M12: -GAMS | N12: - Maximizar o lucro | P12: - A medida de desempenho é maximizar o lucro líquido calculado como os benefícios das vendas menos o custo anual total, dado por instalação de plantas, investimento, produção e transporte custos - A função objetivo é a maximização do lucro líquido anual benefício (ANB) dado pela receita de vendas menos o total anual custo que considera o custo de instalação, o custo de investimento e o custo de transporte, descritos a seguir: - receita de vendas - custo de instalação: custo de instalação da planta - custo de investimento: coeficientes de custo adequados para o estágio j, planta f, para levar em conta a amortização, um fator de encargo de capital no horizonte temporal - custo de transporte: transporte de matérias-primas e produtos - custo de cana-de-açúcar: Este custo abrange o cultivo da cana, a colheita, o transporte, fertilização e trabalho de campo relacionado - custo operacional: considera um custo por tonelada de produto produzido em cada planta - a) O projeto do SC: (i) localização das unidades de produção; (ii) fornecimento de melaço de cada planta de cana-de-açúcar; (iii) etanol e produção de leveduras em cada planta instalada; e, (iv) matéria-prima fluxos de materiais e produtos entre nós SC. b) O projeto de cada uma das plantas instaladas: c) O planejamento detalhado da produção de cada unidade de etanol/planta de levedura | S12: Outro do Corsano MINLP
A13: Poltroniere S.C.; Aliano Filho A.; Caversan A.S.; Balbo A.R.; Florentino H.D.O. | B13: Integrated planning for planting and harvesting sugarcane and energy-cane for the production of sucrose and energy | C13: 10.1016/j.compag.2020.105956 | D13: https://www.scopus.com/inward/record.uri?eid=2-s2.0-85102558107&doi=10.1016%2fj.compag.2020.105956&partnerID=40&md5=e341dc723c32bf132c339236564e6513 | E13: - planejamento integrado do plantio e colheita de cana-de-açúcar e cana-energia para uma usina sucroenergética é proposto para determinar um cronograma otimizado de plantio e colheita, que visa maximizar a produção de sacarose e fibra nos canaviais. - novo modelo de otimização linear inteira mista para o planejamento integrado do plantio e colheita de cana-de-açúcar e cana-energia, de modo que a sacarose obtida da cana-de-açúcar mantenha seu objetivo de produzir açúcar e etanol, enquanto a cana-energia auxilie na produção de energia e etanol de segunda geração. Um método de solução heurística baseado nos princípios das técnicas relax-an-fix e fix-and-optimize é proposto para resolver esses problemas de larga escala, que não podem ser resolvidos por métodos exatos de otimização inteira mista | F13: MILP | G13: - mixed integer linear programming (MILP) | H13: - Heurísticas relax-and-fix e fix-and-optimize | I13: - heurística baseada nos conceitos relax-and-fix e fix-and-optimize - O método é baseado nas heurísticas relax-and-fix e fix-and-optimize, que não têm um caráter de busca quase aleatório como as metaheurísticas clássicas (algoritmos evolucionários, recozimento simulado, busca de vizinhança variável, etc.). - Embora três subproblemas de otimização inteira mista tenham que ser resolvidos para obter uma solução heurística, cada um deles é otimizado mais rapidamente em comparação com a resolução do modelo original (1)–(14). Primeiramente, a maioria das variáveis do modelo estão relacionadas à colheita (tijhd), então relaxando-as e mantendo apenas as variáveis de plantio (xijm) como variáveis binárias diminui substancialmente o esforço na árvore branch-and-bound quando a otimização é feita. Em segundo lugar, embora o subproblema na Fase 2 considere tijhd ÿ {0, 1}, a fixação de variáveis de plantio simplifica o modelo a ser resolvido. As restrições (2)–(5) e consequentemente as restrições (6) são satisfeitas trivialmente. Como o objetivo é minimizar os desvios, basta encontrar uma solução inteira viável para finalizar a busca na árvore branch-and-bound. Finalmente, os subproblemas da Fase 3 aproveitam a estrutura de solução vinda das fases anteriores, fixando variáveis, a fim de acelerar a otimização do objetivo original do modelo. Portanto, a Fase 1 e 2 são consideradas como relax-and-fix e, finalmente, a Fase 3 é o momento de fix-and-optimize. Um fluxograma das heurísticas desenvolvidas é esquematizado na Fig. 2. | J13: AGR | K13: -plantio e colheita | M13: - CPLEX - ambiente de programação Julia, modelagem JuMP - O modelo de otimização foi resolvido pelo software CPLEX Optimization (CPLEX, 2017). A implementação do modelo, bem como a heurística proposta, foram desenvolvidas no ambiente de programação Julia, versão 1.0.4 (Bezanson et al., 2017), utilizando a linguagem de modelagem JuMP versão v0.20 (Dunning et al., 2017). | N13: -Maximizar produção sacarose e fibra | P13: - A função objetivo (1) visa maximizar a produção de sacarose e fibra e minimizar o estoque de sacarose. - objetivo é colher as variedades de cana-de-açúcar o mais próximo possível do pico de maturação, ou seja, maximizar a produção de sacarose. Da mesma forma, pretende-se maximizar a produção de fibra de cana-energia, considerando que sua produtividade aumenta ao longo do tempo, ou seja, é possível colher após 12 meses e então obter um teor de fibra ainda maior | Q13: - Tático | R13: -horizonte de planejamento (safra anual) dividido em períodos (meses)
A14: Li X.; Lu S.; Li Z.; Wang Y.; Zhu L. | B14: Modeling and optimization of bioethanol production planning under hybrid uncertainty: A heuristic multi-stage stochastic programming approach | C14: 10.1016/j.energy.2022.123285 | D14: https://www.scopus.com/inward/record.uri?eid=2-s2.0-85123736368&doi=10.1016%2fj.energy.2022.123285&partnerID=40&md5=da6cbcda171e6fa9f327c8263bf3d580 | E14: - Neste artigo, um modelo de otimização estocástica multiestágio misto é proposto para resolver o problema de planejamento da produção de uma planta de bioetanol com múltiplos matérias-primas considerando simultaneamente a demanda e o rendimento incertos. | F14: SLP | G14: - stochastic optimization model x- mixed multi-stage stochastic optimization model - Este artigo propõe uma abordagem de programação estocástica multiestágio mista para planejamento de produção de bioetanol sob a incerteza híbrida de demanda e rendimento. | I14: - Método heurístico não exato x - um algoritmo heurístico baseado na seleção de avanço rápido é projetado para simplificar a decomposição da árvore de cenários híbridos em larga escala no cenário misto de vários estágios problema de programação estocástica. - To deal with the large-scale scenario tree induced by modelling the hybrid uncertainty, a heuristic algorithm based on fast forward selection is developed to effectively reduce the efforts in searching the redundant scenarios. - Para otimizar o modelo com base na árvore de cenário, este artigo propõe suposições de distribuição de probabilidade, e estima parâmetros de demanda e rendimento com base em dados históricos. - A quarta parte é propor uma abordagem de solução heurística baseada na estratégia de seleção fast-forward para resolver eficientemente o modelo de programação estocástica multiestágio incerto. - O modelo de otimização depende principalmente do número de cenários. Portanto, usar um subconjunto muito menor do que o número de árvores de cenário originais para representar o conjunto de cena original reduzirá muito a complexidade computacional. Alternativamente, estratégias de seleção para frente e para trás fornecem ferramentas eficientes e pesquisam os cenários. O método principal é comparar a diferença entre a média, variância e assimetria de cada cenário e o valor médio, e selecionar o cenário com a menor diferença para reduzir e, finalmente, reduzir o número total de cenários. | K14: - Com base no processo de produção da planta de bioetanol, o modelo proposto é usado para resolver o problema de planejamento da produção sob as condições híbridas de demanda e rendimento incertos. | M14: - O modelo é resolvido no LINGO 11 e no Matlab | N14: - Minimizar custo total de produção - Minimizar o custo de produção de bioetanol e custos de matéria-prima, armazenamento e pedidos em atraso | O14: -Demanda - Rendimento | P14: - A função objetivo Z1 é minimizar o custo total de produção, que inclui quatro custos: os custos de matéria-prima e produção de etanol, o custo de armazenamento de matéria-prima na planta de bioetanol, o custo de armazenamento de bioetanol e o custo de pedidos em atraso no plano de produção fixo - A função objetivo Z2 consiste em duas partes: custo de produção de bioetanol e custos de matéria-prima, armazenamento e pedidos em atraso de uma planta de bioetanol sob condições incertas. - A abordagem de programação estocástica multiestágio proposta visa criar uma ferramenta de decisão de planejamento flexível e eficiente que pode ser implementada na produção de bioetanol, com a capacidade de lidar com a incerteza híbrida de demanda e rendimento para minimizar o custo do consumo de matéria-prima, estoque e pedidos em atraso. | R14: - Neste estudo de caso, um modelo de plano de produção de curto prazo para a planta de bioetanol é estabelecido. Considerando um horizonte de planejamento de 12 dias, onde um dia representa um período de produção. Palha de milho e palha de trigo são usadas como matérias-primas para produzir bioetanol na planta. A biomassa é enviada para a planta de bioetanol usando diferentes métodos de embalagem e é armazenada no depósito de matéria-prima. - assumiu que a demanda em 3 dias consecutivos é estável. Isto a suposição é baseada no prazo de produção do bioetanol. Portanto, 12 períodos de planejamento são divididos em 4 etapas. - No caso deste artigo, 12 dias são primeiramente selecionados como um horizonte de planejamento para análise. Para verificar a viabilidade do modelo para planejamento de médio e longo prazo, o horizonte de planejamento foi estendido para 30 dias.
A15: de Ávila Ribeiro Junqueira R.; Morabito R. | B15: Modeling and solving a sugarcane harvest front scheduling problem | C15: 10.1016/j.ijpe.2019.03.009 | D15: https://www.scopus.com/inward/record.uri?eid=2-s2.0-85063589946&doi=10.1016%2fj.ijpe.2019.03.009&partnerID=40&md5=a12806fadb0be0553f1b9d0e75d81354 | E15: - ter como objetivo minimizar os deslocamentos das frentes de colheita durante a temporada de colheita, mas também minimizar as perdas por moagem da produção industrial e a matéria-prima deixada sem ser colhida nos campos durante toda a temporada. | F15: MILP | G15: - Este artigo apresenta um modelo de Programação Inteira Mista (MIP) para representar e resolver apropriadamente este problema logístico, programando áreas para frentes de colheita e mantendo constantes as capacidades de colheita e transporte. - O modelo foi inspirado no Problema Geral de Dimensionamento e Programação de Lotes com Linhas de Produção Paralelas (GLSPPL) - General Lotsizing and Scheduling Problem with Parallel Production Lines (GLSPPL) | I15: - e apresenta um método heurístico para resolvê-lo, envolvendo um processo de agregação, uma heurística MIP construtiva baseada em relax-and-fix e uma heurística MIP de melhoria baseada em fix-and-optimize - também apresenta um método aproximado para resolver este modelo MIP para instâncias de problemas reais de grande porte usando heurísticas MIP baseadas em relax-and-fix, conforme proposto por Pochet e Wolsey (2006), e baseadas em fix-and-optimize, conforme proposto por Helber e Sahling (2010). | K15: - Colheita e transporte | M15: - GAMS 24.1.3 e CPLEX 12.5.1.0 - O GAMS/CPLEX não conseguiu resolver o modelo devido à falta de memória do computador (mensagem “sem memória”). Portanto, o seguinte os resultados referem-se apenas às soluções da abordagem heurística. | N15: - Miminizar custos com perdas de moagem, perdas de colheita, mudança de frente | P15: - A função objetivo (1) avalia o impacto dos custos do falha na moagem, a cana deixada sem ser colhida e também o deslocamento das frentes de colheita, o que também é considerado, embora seja de grande importância segunda ordem se comparado aos outros dois. - O seguinte modelo MIP minimiza o custo das perdas de moagem (mo) é o custo de oportunidade de uma tonelada de cana-de-açúcar não moída em um período que a produção não atende a demanda mínima mindmt), o custo de perda de cana-de-açúcar deixada no campo (bs é o custo de oportunidade de uma tonelada de cana-de-açúcar deixada sem ser colhida), e o custo das mudanças na frente de colheita (md é o custo unitário da distância percorrida pela frente de colheita para se deslocar de um quarteirão para outro, ou seja, o custo de um km percorrido no transporte o equipamento/máquina) | R15: - planejamento de colheita de toda a temporada de uma usina de açúcar brasileira típica
A16: da Silva A.F.; Marins F.A.S.; Barra Montevechi J.A. | B16: Multi-choice mixed integer goal programming optimization for real problems in a sugar and ethanol milling company | C16: 10.1016/j.apm.2012.12.022 | D16: https://www.scopus.com/inward/record.uri?eid=2-s2.0-84875377451&doi=10.1016%2fj.apm.2012.12.022&partnerID=40&md5=f02fcec187df51170ecc27315df73f1b | E16: - A pesquisa abrange decisões sobre as etapas agrícolas e de corte, carregamento e transporte de cana-de-açúcar por fornecedores e, especialmente, decisões de cogeração de energia; ou seja, a escolha do processo de produção, incluindo etapas de armazenamento e distribuição - Os objetivos desta pesquisa foram desenvolver e aplicar uma Programação Múltipla de Metas Inteiras Mistas (MCMIGP) modelo para um problema real de planejamento de produção agregada em larga escala em uma empresa de moagem de açúcar e etanol, incluindo energia cogeração e comparar esses resultados com aqueles obtidos usando um modelo WGP. Programação de Metas de Peso – WGP | F16: GP-MCMI | G16: - Modelo de Programação de Metas Inteiras Múltiplas Escolhas (MCMI-GP) - Multi-Choice Mixed Integer Goal Programming model (MCMI-GP) | I16: -verificar se é Solver com solução ótima ou uma busca de soluções não exatas | K16: - para planejamento de produção agregada, distribuição e cogeração de energia de uma empresa de moagem de açúcar e etanol. Ambos os modelos foram aplicados a um problema real de planejamento de produção agregada em um - O modelo MCMIGP proposto tem a capacidade de lidar com situações realistas em um ambiente de incertezas e fornece outra ferramenta de decisão para o planejamento de produção agregada de empresas de moagem de açúcar e etanol | M16: GAMS 23.6.2 com o solucionador de otimização CPLEX 12.2.1 | N16: -Metas de custo e produção | P16: - Um MCMIGP é desenvolvido para resolver o problema de planejamento de produção agregada para a empresa de moagem de açúcar e etanol. - (1) Custo variável (GOALh1;GOALh2;GOALh3;GOALh4;GOALh5); - (2) Produção (GOALc1;GOALc2;GOALc3;GOALc4). - GOALh1 Custo de armazenamento desejado [$]; - GOALh2 Custo de transporte de matéria-prima desejado [$]; - GOALh3 Custo de matéria-prima desejado [$]; - GOALh4 Custo de processamento de matéria-prima desejado [$]; - GOALh5 Custo de provedor de transporte desejado [$]; - GOALh6 Custo de coproduto desejado [$]; - GOALc1 Produção desejada de açúcar VHP [tonelada]; - GOALc2 Produção desejada de açúcar VVHP [tonelada]; - GOALc3 Produção desejada de açúcar cristal [tonelada]; - GOALc4 Produção desejada de AEHC [m3]; - GOALc5 Produção desejada de energia [MW]. | R16: - Uma safra | S16: - A pesquisa adotada foi proposta por Bertrand e Fransoo [49] e Bryman e Bell [50], e pode ser classificada como empírico-descritivo aplicado à prática, tendo uma abordagem quantitativa e um procedimento de modelagem técnica | T16: Metodologia modelo para otimização | U16: confidencialidade, trabalhamos com valores econômicos proporcionais em conformidade com as condições do CM para fornecer o dados para esta pesquisa.
A17: Corsano G.; Aguirre P.A.; Montagna J.M. | B17: Multiperiod design and planning of multiproduct batch plants with mixed-product campaigns | C17: 10.1002/aic.11854 | D17: https://www.scopus.com/inward/record.uri?eid=2-s2.0-69049087107&doi=10.1002%2faic.11854&partnerID=40&md5=6c168665ffab8ee6df64f27a1f74debf | E17: - aplicado a uma planta de fermentação em batelada para produzir dois produtos: levedura para ração de gado e etanol que no modelo são chamados de A e B. - Neste trabalho, um modelo MINLP geral é proposto para o otimização simultânea do projeto, operação, programação e planejamento de uma planta de lote multiprodutos, considerando uma abordagem multiperíodo. - Esta abordagem é proposta para uma rede de fermentadores com alto nível de detalhes na descrição das operações unitárias em uma planta que produz levedura e etanol. | F17: MINLP | G17: - mixed integer nonlinear program (MINLP) - modelo de otimização multiperíodo | I17: - modelo de campanha de produtos mistos MPC - the problem of sizing and scheduling of a multiproduct batch plant for the unlimited intermediate storage and zero wait (ZW) transfer policies with mixed-product campaigns (MPCs) - modelo determina o MPC ideal a partir de um conjunto de diferentes campanhas propostas pelo designer segundo heurísticas critérios, onde a seleção da campanha é modelada por meio de variáveis binárias - Trapezoidal ? | K17: - otimização integral dos processos de fermentação | M17: - GAMS 20 - O código DICOPT foi usado para resolver os problemas MINLP | N17: -Maximizar lucro líquido total | P17: - A função objetivo adotada é a maximização do benefício líquido total dado pela expressão: onde Qit é o período de produção do produto i e pit seu preço de venda, e Vj representa o tamanho dos fermentadores - os recursos r são melaço (M), suco de filtro (FJ), vinhaça de destilaria (DV) e água doce (FW) | R17: -diferentes configurações de campanha são propostas para cada período de tempo e são manipulados em termos de variáveis binárias.
A18: Kantas A.B.; Cobuloglu H.I.; Büyüktahtakn I.E. | B18: Multi-source capacitated lot-sizing for economically viable and clean biofuel production | C18: 10.1016/j.jclepro.2015.02.001 | D18: https://www.scopus.com/inward/record.uri?eid=2-s2.0-84928768228&doi=10.1016%2fj.jclepro.2015.02.001&partnerID=40&md5=15fc26072e55b1570a5109d825726e84 | E18: Neste artigo, desenvolvemos um modelo de dimensionamento de lote capacitado por programação linear inteira mista (MILP) para analisar a viabilidade econômica e ambiental da produção de etanol usando múltiplas fontes de biomassa. O modelo minimiza o custo da produção de etanol enquanto penaliza seus possíveis impactos ambientais adversos, como emissões de CO2 e uso excessivo de água. - Neste artigo, apresentamos um modelo de dimensionamento de lote MILP que define o design ideal da produção de etanol a partir de diferentes fontes de biomassa. O objetivo deste modelo é minimizar o custo total, bem como os impactos ambientais negativos totais, como emissões excessivas de CO2 e uso de água. Até onde sabemos, este estudo é o primeiro a fornecer um modelo de dimensionamento de lote MILP que considera os impactos econômicos e ambientais da produção de etanol. O modelo proposto é aplicado a um estudo de caso real de um local de produção de biocombustível em Hugoton, Kansas, usando quatro fontes de biomassa diferentes: capim-rabo-de-raposa, cana-de-açúcar, milho e trigo. | F18: MILP | G18: - mixed-integer linear programming (MILP) capacitated lot-sizing model | I18: - abordagem de dimensionamento de lote capacitado, na qual a quantidade de capacidade de produção e matéria-prima de biomassa disponível são limitadas. - modelo de dimensionamento de lote capacitado por MILP com restrições de emissões de CO2 e uso de água que é aplicado à produção de biocombustíveis. | M18: - IBM Ilog Cplex 12.5 | N18: - Minimizar custo total - Custos aquisição matéria-prima, instalação, estoque, penalidade por emissões de carbono, uso excessivo de água | P18: - A função objetivo do modelo MILP inclui custos de produção, custos de instalação e custos de compra de biomassa menos crédito fiscal para cada galão de etanol produzido e renda da produção de eletricidade, bem como custos de manutenção de estoque e uma penalidade fiscal pela quantidade excessiva de emissões de CO2 e uso excessivo de água durante a produção - minimizar o custo total da produção de etanol, manutenção de estoque e compra de biomassa, bem como o custo de penalidade em relação ao uso excessivo de água e emissões de CO2. | R18: - Neste estudo, consideramos um horizonte de planejamento de um ano consistindo de 26 períodos, onde cada período representa um período de duas semanas.
A19: You F.; Tao L.; Graziano D.J.; Snyder S.W. | B19: Optimal design of sustainable cellulosic biofuel supply chains: Multiobjective optimization coupled with life cycle assessment and input-output analysis | C19: 10.1002/aic.12637 | D19: https://www.scopus.com/inward/record.uri?eid=2-s2.0-80052359753&doi=10.1002%2faic.12637&partnerID=40&md5=5750c8e9fda0ae83c38a59510192ad22 | E19: - modelo de programação linear inteira mista multiobjetivo (mo-MILP) é desenvolvido para levar em conta as principais características das cadeias de suprimento de etanol celulósico, incluindo sazonalidade do suprimento e diversidade geográfica, degradação de biomassa, densidade de matéria-prima, diversas vias de conversão e subprodutos, compatibilidade de infraestrutura, distribuição de demanda, economia regional e incentivos governamentais. | F19: MILP-MO | G19: -multiobjective mixed-integer linear programming (mo-MILP) model | I19: - e-constraint method; and the resulting Pareto-optimal - O problema mo-MILP é resolvido com um método de restrição eletrônica; e as curvas Pareto-ótimas resultantes revelam o tradeoff entre as dimensões econômica, ambiental e social das cadeias de suprimento de biocombustíveis sustentáveis - Neste artigo, combinamos técnicas de LCA com uma abordagem de programação matemática, criando um método sistemático que permite a geração e avaliação automática de processos e alternativas à cadeia de abastecimento que podem levar a benefícios ambientais e económicos significativos - Especificamente, adotamos técnicas clássicas de LCA baseadas em processos, seguindo os princípios e padrões estabelecidos em ISO14040 - Quantificação dos impactos sociais através de input-output análise - social dimensions of sustainability for the entire cellulosic biofuel supply chain based on life cycle analysis (LCA) and economic input–output (EIO) analysis | K19: - Uma cadeia de fornecimento típica de biomassa celulósica para biocombustíveis inclui cinco elementos principais: sistema de produção de biomassa, sistema de logística de biomassa, sistema de produção de biocombustível, biocombustível sistema de distribuição e uso final do biocombustível - tomada de decisões em múltiplos períodos temporais e escalas espaciais e simultaneamente prevê o melhor projeto de rede, localização de instalações, seleção de tecnologia, investimento de capital, operações de produção, controle de estoque e decisões de gestão logística | M19: - O modelo MILP foi codificado em GAMS 23.4.3 e resolvido com o solver CPLEX 12. - Modelos de processo baseados em Aspen Plus - O modelo também é integrado com o LCA e o EIO por meio de um esquema de otimização multiobjetivo para levar em conta os aspectos econômicos, objetivos ambientais e sociais. - IMPLAN Professional46 e do JEDI O modelo 44 é usado para quantificar os empregos acumulados | N19: - minimizar o custo total anualizado - minimizar as emissões de carbono - maximizar o número de empregos locais acumulados | P19: - otimização multiobjetivo - 3 objetivos: Os objetivos são maximizar o desempenho econômico, ambiental e social do biocombustível celulósico. - o objetivo econômico é definido em (41). O objetivo ambiental, que é modelado com base nos princípios do LCA, é definido em (42). A equação (43) define o número de empregos anuais equivalentes em tempo integral acumulados regionalmente, que é o objetivo social com base na análise EIO. - Objetivo econômico - minimizar o custo total anualizado - Objetivo ambiental - minimizar as emissões de GEE (CO2-equivalente/ano) - Objetivo social - maximizar o número de empregos locais acumulados (equivalente a tempo inteiro durante um ano) | R19: - O horizonte de planejamento de um ano é dividido em uma série de períodos de tempo. | S19: Explica bem detalhado o processo de fabricação do bioetanol (etanol celulósico)
A20: de Ávila Ribeiro Junqueira R.; Morabito R. | B20: Optimization approaches for sugarcane harvest front programming and scheduling | C20: 10.1590/0104-530X1882-16 | D20: https://www.scopus.com/inward/record.uri?eid=2-s2.0-85025139132&doi=10.1590%2f0104-530X1882-16&partnerID=40&md5=db90ddf501543c3f83096068037a53e3 | E20: - problema de programação e sequenciamento das frentes de colheita em usinas de cana-de açúcar | F20: MILP | G20: - programação inteira mista | I20: - problema geral de dimensionamento e sequenciamento de lotes com linhas de produção em paralelo (GLSPPL – General Lot-sizing and Scheduling Problem for Parallel Production Lines) proposto por Meyr (2002) - GLSPPL com conservação de setup, inspirado nos estudos em Meyr (2002) e Meyr & Mann (2013) - lot sizing and scheduling problem on parallel machines with sequence-dependent setup times and costs - modelo de dimensionamento e sequenciamento de lotes da produção em máquinas paralelas, com custos e tempos de setup dependentes da sequência | K20: - Sequenciamento das frentes de colheita | M20: - Os Modelos 1, 1A e 1B foram codificados em GAMS 24.1.3 e resolvidos otimamente pelo CPLEX 12.5.1.0. | N20: -Maximizar a colheita nos períodos mais favoráveis - Minimizar deslocamento das frentes de colheita - Minimizar custos de deslocamento da frente, perda de moagem e de não colher matéria-prima | P20: - A função objetivo 1 maximiza a preferência por colher os blocos nos períodos mais favoráveis dentro da janela de tempo. - Modelo 1A: mínimo deslocamento das frentes: Entretanto, como com essa modificação o tempo de setup deixa de ser considerado no modelo, altera-se a função objetivo para a Equação 17 de forma a minimizar esse tempo de deslocamento das frentes de colheita - Modelo 1B: mínimos custos de deslocamento da frente, perda de moagem e de não colher matéria-prima: foram inseridas variáveis de folga nas restrições de produção e demanda, sendo essas variáveis penalizadas na função objetivo com base em seu custo unitário. Os custos de deslocamento da frente de colheita estão presentes na função objetivo, mas podem ser considerados como de segunda ordem, servindo principalmente como critério de desempate. | R20: - horizonte de planejamento multi-períodos (e.g., semanas ou meses de uma safra)
A21: Hafezi N.; Sheikhdavoodi M.J.; Bahrami H.; Alavi S.E. | B21: Optimization of Harvesting Priority of Sugarcane Farms by the Generalized Assignment Problem | C21: 10.1007/s12355-023-01336-2 | D21: https://www.scopus.com/inward/record.uri?eid=2-s2.0-85180642228&doi=10.1007%2fs12355-023-01336-2&partnerID=40&md5=613bd353d7aa58e5ca53c386c2cee26f | E21: - O objetivo deste estudo foi otimizar a alocação de fazendas de cana-de-açúcar para os períodos de colheita com base em parâmetros preditivos de rendimento de cana-de-açúcar e porcentagem de açúcar recuperável. -problema de atribuição generalizada na forma de programação inteira mista para modelar o melhor tempo de colheita de fazendas de cana-de-açúcar em um horizonte de 7 meses - para otimizar o tempo de colheita das fazendas, dois parâmetros críticos de rendimento de cana-de-açúcar e porcentagem de açúcar recuperável foram previstos por um sistema de agrupamento fuzzy c-means. | F21: MILP-FL | G21: - Fuzzy mixed integer linear programing (MILP) x- programação inteira mista - Mixed integer programming | I21: - fuzzy c-means clustering system - sistema de agrupamento fuzzy c-means. - Um sistema de inferência neuro-fuzzy adaptativo (ANFIS) baseado em agrupamento c-means foi usado para prever os parâmetros. - adaptive neuro-fuzzy inference system (ANFIS) based on c-means clustering - baseado no algoritmo branch and cut foi usado para implementar o modelo e atingir a alocação ótima de fazendas de cana-de-açúcar. | K21: - Tempos de colheita | M21: - GAMS versão 24.1 com um solucionador CPLEX. - o software MATLAB versão 2017b foi usado para prever os parâmetros modelados pelo sistema de inferência fuzzy | N21: -Maximizar o lucro da colheita, no melhor período, maior quantidade prevista de açúcar recuperável | P21: - é a função objetivo do problema, que busca maximizar o lucro bruto da colheita de cada fazenda de cana-de-açúcar no melhor período em termos da maior quantidade prevista de açúcar recuperável. - estimando os valores previstos durante os sete períodos de colheita (novembro-maio) de 2018-2019, os custos variáveis da colheita e transporte da cana-de-açúcar, o custo de pontualidade da operação e a renda da produção de açúcar branco e etanol foram calculados. | R21: - horizonte de 7 meses (uma safra). - sete períodos de colheita (novembro-maio) de 2018-2019 | S21: - A cana-de-açúcar é uma planta perene adequada para climas quentes e úmidos. O principal produto extraído da cana-de-açúcar é o açúcar, que varia de acordo com a variedade, as condições geográficas e climáticas. A porcentagem de recuperação de açúcar durante 2019–2020 em diferentes países foi de 8,07–14,08%. Assim, a maior recuperação de açúcar foi observada na Austrália, seguida pelo Brasil, EUA, Colômbia, Tailândia, Índia, México, Argentina e Paquistão (Ram e Karuppaiyan 2021).
A22: de Paiva R.P.O.; Morabito R. | B22: Optimization of the hierarchical production planning of a cooperative society of sugarcane milling companies; [Otimização do planejamento hierárquico da produção em usinas cooperadas do setor sucroenergético] | C22: 10.1590/S0103-65132012005000077 | D22: https://www.scopus.com/inward/record.uri?eid=2-s2.0-84886552472&doi=10.1590%2fS0103-65132012005000077&partnerID=40&md5=f5b753a9bd3304102bb0cd8145474047 | E22: - modelo de otimização para o planejamento agregado da produção em usinas cooperadas do setor sucroenergético. Esta modelagem considera a relação hierárquica existente entre o planejamento anual da cooperativa e o planejamento tático de safra das usinas cooperadas. No nível de decisão da cooperativa, o modelo indica a meta de produção de cada usina e define a política de estocagem e de atendimento da demanda. No nível de decisão de uma usina cooperada, o modelo possibilita definir a quantidade de cana-de-açúcar colhida, a quantidade transportada por prestador de serviço, a seleção dos processos de produção de açúcar, álcool, melaço e energia elétrica | F22: MILP | G22: - os modelos de programação linear e programação inteira mista | M22: - GAMS, versão 22.7, com solver CPLEX 11 | N22: - maximiza a margem de contribuição ao lucro da produção dos produtos - maximiza a margem de contribuição agroindustrial de produção dos produtos p, por meio dos processos k, da matéria-prima m, do tipo de transporte da matéria-prima f, em todos os períodos t, incluindo a receita de energia exportada. | P22: - pretende-se definir o mix de produção de cada unidade, a política de estocagem e de comercialização de toda a produção dos açúcares, dos alcoóis e dos melaços. - Nível 1: A função objetivo 1 do modelo estratégico CRPAAA maximiza a margem de contribuição ao lucro da produção dos produtos p, em cada usina u, em todos os períodos t, considerando também os custos com a política de estoque e o atendimento da demanda. - Nível 1: Este modelo determina a quantidade e o mix de produção (PUput) das usinas, a política de estoque (Ipet) e a política de atendimento da demanda (Dpt) da CRPAAA. Essas variáveis devem ser calculadas de forma que a margem de contribuição do grupo seja maximizada e as restrições de mercado, previsão de safra, capacidade de transporte das frotas e capacidade de estoque sejam respeitadas. - Nível 2: A função objetivo 15 do modelo PASUC/N2 maximiza a margem de contribuição agroindustrial de produção dos produtos p, por meio dos processos k, da matéria-prima m, do tipo de transporte da matéria-prima f, em todos os períodos t, considerando a remuneração decorrente da participação percentual do resultado obtido pela CRPAAA e incluindo a receita de energia exportada. | R22: - O modelo adota um horizonte de planejamento de médio prazo (período de um ano) - No primeiro nível (planejamento da CRPAAA para o ano safra), tem-se um modelo de PL, multiproduto, dois estágios, dinâmico, capacitado, com horizonte de planejamento anual e agregação temporal mensal. No segundo nível (planejamento da USC para os meses de safra), tem-se um modelo de PIM monoestágio, multiprocesso (ou multiproduto), dinâmico e que combina decisões de dimensionamento e sequenciamento de lotes para o atendimento das metas do primeiro nível hierárquico. - o modelo proposto possui um primeiro nível (mais estratégico) de planejamento agregado, com horizonte de planejamento de um ano safra - No segundo nível (tático) do modelo de planejamento agregado, o horizonte passa a ser o período de safra ou um subperíodo dele, dividido em períodos semanais, e existe uma menor agregação com relação ao nível de análise dos processos produtivos da empresa. | S22: - Atualmente não são utilizados recursos de otimização para auxiliar nessas atividades da CRPAAA. Este planejamento é executado com base no histórico de produção das usinas, nas informações do mercado de açúcar e álcool e na relação comparativa entre o preço dos produtos pertencentes ao mix da cooperativa. | T22: - Modelo considera consumo de vapor na planta, balanço térmico e energético | U22: - 4.3.5. Parâmetros do cálculo da matriz de rendimentos (Apkt) - Apresenta os calculos de rendimento e conversão, pureza, recuperação de açúcar, sacarose, melaço, rendimento industrial... com referências
A23: de Ávila Ribeiro Junqueira R.; Morabito R. | B23: Programming and scheduling sugarcane harvesting fronts: Model and solution methods for large-scale problems | C23: 10.1590/0104-530X2647-16 | D23: https://www.scopus.com/inward/record.uri?eid=2-s2.0-85045447528&doi=10.1590%2f0104-530X2647-16&partnerID=40&md5=b5fd1133a34f9a34589e2d5ffaafcd40 | E23: - otimização para a programação e o sequenciamento das frentes de colheita de cana-de-açúcar foram propostos. Esse é um problema agrícola e logístico complexo que envolve vários fatores, tais como o estágio de maturação da matéria-prima, a colheita na unidade agrícola e o transporte dessa matéria-prima para a unidade industrial, bem como a capacidade de moagem da unidade industrial. | F23: MILP | G23: - programação inteira mista - Mixed integer programming | I23: - Agregação de blocos, heurística construtiva (Relax-and-fix), heurística de melhoria (Fix-and-optimize) - problema geral de dimensionamento e sequenciamento de lotes com linhas de produção em paralelo (GLSPPL – General Lot-sizing and Scheduling Problem for Parallel Production Lines) - métodos baseados em heurísticas PIM para resolver esse modelo em uma situação real de uma safra de uma empresa típica do setor, inspirados em uma heurística de agregação de blocos de colheita, em heurísticas de construção do tipo relax-and-fix e heurísticas de melhoria do tipo fix-and-optimize. - utiliza um modelo de PIM para representar o problema de programação e sequenciamento de frentes de colheita de cana-de-açúcar e propõe métodos heurísticos para sua resolução em situações reais, envolvendo três heurísticas integradas: uma heurística de agregação de blocos de colheita, uma heurística construtiva baseada na heurística de PIM relax-and-fix e uma heurística de melhoria baseada na heurística de PIM fix-and-optimize. - A primeira etapa do método proposto foi de agregação dos blocos de colheita, de tal forma que não se descaracterizassem variáveis como a distância do bloco em relação à usina e o potencial de colheita. A segunda etapa envolveu proposição de métodos heurísticos baseados em PIM, como relax-and-fix, para construir uma boa solução inicial factível. A terceira etapa envolveu a utilização do método fix-and-optimize, para buscar a melhoria da solução construída na etapa 2 | K23: - Planejamento de colheita e transporte | M23: - GAMS versão 24.1.3, utilizando-se como solver o CPLEX 12.5.1.0 | N23: - Minimiza os custos de falha na moagem, cana bisada e deslocamento das frentes de colheita | P23: - A Função Objetivo 1 avalia o impacto dos custos de falha na moagem, cana bisada e deslocamento das frentes de colheita, que também é considerado, embora seja de segunda ordem se comparado aos outros dois | R23: - No caso da empresa estudada, que é uma usina de médio porte, ela possuía para a safra estudada cinco frentes de colheita, oito meses de safra (macroperíodos), com 200 dias efetivos de safra e um tempo de permanência médio de três dias da frente por bloco.
A24: Al Mohamed A.A.; Al Mohamed S.; Ahmad M. | B24: Solving aggregate production planning problem with uncertainty using fuzzy goal programming | C24: 10.1504/IJMOR.2023.132838 | D24: https://www.scopus.com/inward/record.uri?eid=2-s2.0-85170406640&doi=10.1504%2fIJMOR.2023.132838&partnerID=40&md5=4912897a496be357a18091b25c770ea4 | E24: - Planejamento agregado de produção (APP) - aggregate production planning - modelo de programação de metas fuzzy (FGP) para abordar o problema de planejamento no ambiente de trabalho, especialmente no campo da produção, e os fatores que afetam o planejamento da produção. - Este artigo teve como objetivo resolver o problema do planejamento de produção agregada em corporações gerais para a indústria açucareira, de uma forma que ajude os tomadores de decisão a tomar decisões apropriadas, especialmente sob o ambiente fuzzy em que todas as empresas de produção de açúcar operam, identificando variáveis de decisão, níveis de aspiração e tolerância. - Portanto, a produção de beterraba para a indústria açucareira no país é considerada um dos principais pilares neste setor, mas esta produção cobre apenas (20%) da necessidade do estado | F24: GP-FL | G24: - modelo de programação de metas fuzzy (FGP) - fuzzy goal programming (FGP) | I24: - tolerance approach to FGP | K24: - O primeiro passo para entender o problema do estudo é entender o mapa do processo industrial do empreendimento, que inclui as subdivisões do fluxo da beterraba e as etapas pelas quais a beterraba passa, dividido em cinco etapas: pesagem, moagem (bagaço), clarificação, evaporação, cristalização - eficiência de cada estágio do processo de produção é estimada conhecendo a quantidade de desperdício e os períodos de espera durante o processo de fabricação. | M24: - programa GAMS | N24: - Minimizar os custos totais de produção - Minimizar os custos totais de armazenamento - Minimizar as alterações nos níveis de mão-de-obra | P24: - reduzir o custo de produção e armazenamento e a mudança no nível da força de trabalho - Notamos que a primeira função objetivo consiste em duas partes. A primeira parte inclui o custo unitário de produção do produto (i) no período (t), e a segunda parte inclui o custo total necessário para usar as variáveis da força de trabalho durante o período (t). - Multiobjetivo: Minimizar os custos totais de produção; Minimizar os custos totais de armazenamento; Minimizar as alterações nos níveis de mão-de-obra | R24: - O prazo médio é limitado a um período de 3 a 18 meses | S24: - O prazo médio é limitado a um período de 3 a 18 meses, no qual os melhores níveis de produção, mão de obra e níveis de estoque são determinados para cada período de planejamento, levando em consideração todos os recursos e capacidades de produção para atender à demanda esperada para um determinado produto ou grupo de produtos, levando em consideração a qualidade da produção consistente com o objetivo do nosso estudo atual. A diferença entre a definição de planejamento de produção e APP é que quando o planejamento é 'agregado', isso indica que ele não se concentra em um tipo específico de produto ou serviço, mas sim combina categorias homogêneas de produtos ou serviços em grupos sem se referir aos detalhes exatos do produto ou serviço. - referência sobre lógica Fuzzy
A25: Awudu I.; Zhang J. | B25: Stochastic production planning for a biofuel supply chain under demand and price uncertainties | C25: 10.1016/j.apenergy.2012.09.025 | D25: https://www.scopus.com/inward/record.uri?eid=2-s2.0-84871810249&doi=10.1016%2fj.apenergy.2012.09.025&partnerID=40&md5=3a247c6286068a38cbf82e1f58a32fb1 | E25: - planejamento de produção estocástico para uma cadeia de suprimentos de biocombustíveis sob incertezas de demanda e preço. A cadeia de suprimentos consiste em fornecedores de biomassa, plantas de refinaria de biocombustíveis e centros de distribuição. - Decisões como a quantidade de matérias-primas compradas, a quantidade de matérias-primas consumidas e a quantidade de produtos produzidos são consideradas. - uma cadeia de suprimentos representativa para uma usina de etanol em Dakota do Norte é considerada | F25: SLP | G25: - stochastic linear programming model - programação linear estocástico é proposto dentro de uma estrutura de planejamento de período único para maximizar o lucro esperado. - - A stochastic linear programming model is proposed, and the uncertainties are incorporated in the demand and price of the finished products. - Um modelo de programação linear estocástica é proposto, e as incertezas são incorporadas na demanda e no preço dos produtos acabados. - Primeiro, apresentaremos um modelo determinístico para fins de comparação e, em seguida, proporemos um modelo estocástico para obter lucro esperado mais alto. | I25: - Heurística com Benders, com método de Monte Carlo x- Benders decomposition (BD) with Monte Carlo simulation technique - A decomposição de Benders (BD) com técnica de simulação de Monte Carlo é aplicada para resolver o modelo proposto - uma estrutura de simulação é desenvolvida para comparar os desempenhos do modelo determinístico e do modelo estocástico proposto - A decomposição de Benders é capaz de resolver programação matemática em larga escala, especialmente em casos estocásticos, dada uma certa estrutura de bloco. Os problemas são divididos em problemas principais e subproblemas, onde o problema principal contém a parte determinística, e o subproblema tem a parte estocástica. Ao resolver o subproblema, a técnica de simulação de Monte Carlo é aplicada a cenários aleatórios gerais. | K25: - O problema é modelado como um problema de programação estocástica, com decisões importantes como volume de produção de produtos, quantidade de matéria-prima adquirida e a quantidade de matéria-prima consumida. - a primeira fase decisões são a quantidade inicial de matérias-primas compradas, volumes de produtos finais a serem produzidos e a matéria-prima consumida. - Decisões como a quantidade de produtos finais vendidos, pendências e vendas perdidas são consideradas decisões de segundo estágio. Isto significa adiar o resto das decisões para o próximo período após a realização da incerteza. - a cadeia de suprimentos consiste em três camadas: fontes de matérias-primas de biomassa, plantas de refino de biocombustíveis e centros de distribuição. | M25: - O problema é resolvido usando programas MATLAB e GAMS | N25: - Maximizar o lucro | O25: - Demandas e preços dos produtos | P25: - O objetivo do problema é maximizar o lucro da planta de biorrefinaria considerando decisões como: (1) a quantidade de matérias-primas compradas de cada fornecedor, (2) a quantidade de produtos produzidos, (3) a quantidade de produtos vendidos, (4) a quantidade de matérias-primas consumidas e (5) os produtos finais e o estoque de matérias-primas deixados no primeiro estágio - programação linear estocástico é proposto dentro de uma estrutura de planejamento de período único para maximizar o lucro esperado - O objetivo deste artigo é maximizar o lucro de um sistema de cadeia de suprimentos multiproduto, de período único e três escalões, sujeito a incertezas nas demandas e preços dos produtos finais. - A função objetivo (1) maximizar o lucro, que é igual à receita menos o custo total. A receita inclui o total vendas de biocombustível e subprodutos. O custo total consiste no custo de compra de matérias-primas, no custo de transporte para matérias-primas e produtos finais, e nos custos de manutenção de estoque para matérias-primas e produtos finais. Outros custos são o custo de vendas com perdas e custos de pedidos em carteira, bem como o custo de processamento de matérias-primas em produtos finais. - A função objetivo (Eq. (12)) é maximizar o lucro esperado, que pode ser obtido subtraindo o custo total esperado da receita esperada. Devido às demandas e preços incertos dos produtos finais, a primeira parte da Eq. (12) é usada para calcular a receita esperada considerando a probabilidade de cada cenário. O custo total compreende o custo de compra de matérias-primas, o custo de transporte de matérias-primas, o custo de produção de produtos finais, o custo esperado de manutenção de estoque de matérias-primas e produtos finais, vendas perdidas esperadas e o custo esperado de backlog.
A26: de Paiva R.P.O.; Morabito R. | B26: Stochastic robust optimization model applied to the aggregate production planning in mill cooperative socities in the sugar-energy sector; [Programação estocástica robusta aplicada ao planejamento agregado de safra em usinas cooperadas do setor sucroenergético] | C26: 10.1590/S0104-530X2011000400004 | D26: https://www.scopus.com/inward/record.uri?eid=2-s2.0-84856675703&doi=10.1590%2fS0104-530X2011000400004&partnerID=40&md5=199c3b71d25f358c30aa00b77d1f6dbb | E26: - modelo de programação estocástica robusta aplicado ao planejamento agregado da produção em usinas cooperadas do setor sucroenergético. Esta modelagem considera a relação hierárquica existente entre o planejamento anual da cooperativa e o planejamento tático de safra das usinas cooperadas, além de contemplar importantes incertezas existentes nos parâmetros de entrada do modelo | F26: SLP-RO | G26: - modelo de programação estocástica robusta - Para resolver os problemas de programação linear e programação inteira mista | I26: - Neste artigo, a incorporação de incertezas no processo de planejamento é feita por meio da aplicação da técnica de programação estocástica robusta, inicialmente proposta por Mulvey, Vanderbei e Zenios (1995). - integração de conceitos de programação de metas e de programação estocástica em dois estágios com recurso - Incerteza nos preços dos produtos (PASUC/N1-M-VP) - Incerteza na matriz de rendimentos industriais (PASUC/N2-M-A) | K26: - Indústria | M26: - linguagem de modelagem GAMS, versão 22.7, com o solver CPLEX 11 | N26: - Maximiza a receita variável de todos os setores agroindustriais | O26: - Preços e rendimento industrial | P26: - incorpora a modelagem de programação estocástica robusta, com características de programação multiobjetivo *** do artigo de 2009 referente ao modelo do artigo PASUC/N1 e PASUC/N2 *** - A função objetivo (1) maximiza a receita variável total de todos os setores agroindustriais. etapas da usina. Esta função objetivo auxilia o tomador de decisão a determinar a quantidade de cana-de-açúcar moída, a seleção de fornecedores de cana-de-açúcar, a seleção de cana-de-açúcar fornecedores de transporte, a seleção do processo industrial utilizado na produção de açúcar, etanol e melaço e as decisões de armazenagem relacionadas aos produtos finais visando atingir a receita máxima em toda a temporada de colheita | R26: - planejamento anual da cooperativa e o planejamento tático de safra das usinas cooperadas
A27: Na última linha da tabela de classificação, fazer a classificação do artigo

Sheet Publicações Autor
A1: Autor | B1: País | C1: Publicações | E1: Autor | F1: Quantidade
A2: Morabito, Reinaldo | B2: Brasil | C2: 8 | E2: 34 demais autores (Países diversos) | F2: 1
A3: de Paiva, Rafael Piatti Oiticica | B3: Brasil | C3: 5 | E3: Wang, Y. (China) | F3: 2
A4: de Ávila Ribeiro Junqueira, Rogério | B4: Brasil | C4: 3 | E4: Montagna, J.M. (Argentina) | F4: 2
A5: Lu, Shan | B5: China | C5: 2 | E5: Marins, F.A.S. (Brasil) | F5: 2
A6: Marins, Fernando Augusto Silva | B6: Brasil | C6: 2 | E6: Li, X. (China) | F6: 2
A7: Li, Zhe | B7: China | C7: 2 | E7: da Silva, A.F. (Brasil) | F7: 2
A8: Wang, Yue | B8: China | C8: 2 | E8: Corsano, G. (Argentina) | F8: 2
A9: da Silva, Aneirson Francisco | B9: Brasil | C9: 2 | E9: Aliano Filho, A. (Brasil) | F9: 2
A10: Corsano, Gabriela | B10: Argentina | C10: 2 | E10: Lu, S. (China) | F10: 2
A11: Montagna, Jorge M. | B11: Argentina | C11: 2 | E11: Li, Z. (China) | F11: 2
A12: Li, Xinchao | B12: China | C12: 2 | E12: de Ávila Ribeiro Junqueira, R. (Brasil) | F12: 3
A13: Aliano Filho, Angelo | B13: Brasil | C13: 2 | E13: de Paiva, R.P.O. (Brasil) | F13: 5
A14: Fumero, Yanina | B14: Argentina | C14: 1 | E14: Morabito, R. (Brasil) | F14: 8
A15: Kantas, Alperen Burak | B15: Estados Unidos | C15: 1
A16: You, Fengqi | B16: Estados Unidos | C16: 1
A17: Melo, Teresa | B17: Alemanha | C17: 1
A18: Poltroniere, Sônia Cristina | B18: Brasil | C18: 1
A19: Pato, Margarida Vaz | B19: Portugal | C19: 1
A20: Aguirre, Pío A. | B20: Argentina | C20: 1
A21: Aguayo, Maichel M. | B21: Chile | C21: 1
A22: Graziano, Diane J. | B22: Estados Unidos | C22: 1
A23: Cao, Jiangtao | B23: China | C23: 1
A24: Büyüktahtakn, I. Esra | B24: Estados Unidos | C24: 1
A25: Montevechi, José Arnaldo Barra | B25: Brasil | C25: 1
A26: Balbo, Antonio Roberto | B26: Brasil | C26: 1
... A47: Zhang, Jun | B47: Estados Unidos | C47: 1
A48: Total Geral | C48: 68

Sheet Qtde Citações
A1: Classificação | B1: A
A3: Rótulos de Linha | B3: Year | C3: Soma de Cited by
A4: Optimal design of sustainable cellulosic biofuel supply chains: Multiobjective optimization coupled with life cycle assessment and input-output analysis | B4: 2012 | C4: 602
A5: Stochastic production planning for a biofuel supply chain under demand and price uncertainties | B5: 2013 | C5: 122
A6: An optimization model for the aggregate production planning of a Brazilian sugar and ethanol milling company | B6: 2009 | C6: 51
A7: A Fuzzy Goal Programming model for solving aggregate production-planning problems under uncertainty: A case study in a Brazilian sugar mill | B7: 2014 | C7: 50
A8: Multi-choice mixed integer goal programming optimization for real problems in a sugar and ethanol milling company | B8: 2013 | C8: 40
A9: Modeling and solving a sugarcane harvest front scheduling problem | B9: 2019 | C9: 40
A10: Multi-source capacitated lot-sizing for economically viable and clean biofuel production | B10: 2015 | C10: 26
A11: Designing a hub location model in a bagasse-based bioethanol supply chain network in Iran (case study: Iran sugar industry) | B11: 2019 | C11: 20
A12: Optimization approaches for sugarcane harvest front programming and scheduling | B12: 2017 | C12: 16
A13: Integrated planning for planting and harvesting sugarcane and energy-cane for the production of sucrose and energy | B13: 2021 | C13: 14
A14: A bi-objective mathematical model for integrated planning of sugarcane harvesting and transport operations | B14: 2021 | C14: 13
A15: Modeling and optimization of bioethanol production planning under hybrid uncertainty: A heuristic multi-stage stochastic programming approach | B15: 2022 | C15: 12
... A26: Optimization of Harvesting Priority of Sugarcane Farms by the Generalized Assignment Problem | B26: 2024 | C26: 0
A27: Total Geral | C27: 1056
